{
	"entries" : 
	[
		{
			"name" : "BIBER_COMPILER",
			"properties" : 
			[
				{
					"name" : "ADVANCED",
					"value" : "1"
				},
				{
					"name" : "HELPSTRING",
					"value" : "Path to a program."
				}
			],
			"type" : "FILEPATH",
			"value" : "BIBER_COMPILER-NOTFOUND"
		},
		{
			"name" : "BIBTEX_COMPILER",
			"properties" : 
			[
				{
					"name" : "ADVANCED",
					"value" : "1"
				},
				{
					"name" : "HELPSTRING",
					"value" : "Path to a program."
				}
			],
			"type" : "FILEPATH",
			"value" : "BIBTEX_COMPILER-NOTFOUND"
		},
		{
			"name" : "BUILD_SHARED_LIBS",
			"properties" : 
			[
				{
					"name" : "HELPSTRING",
					"value" : "Build shared libraries"
				}
			],
			"type" : "BOOL",
			"value" : "OFF"
		},
		{
			"name" : "CLANG_FORMAT_EXE",
			"properties" : 
			[
				{
					"name" : "HELPSTRING",
					"value" : "Path to a program."
				}
			],
			"type" : "FILEPATH",
			"value" : "/opt/homebrew/opt/llvm/bin/clang-format"
		},
		{
			"name" : "CLANG_FORMAT_PROGRAM",
			"properties" : 
			[
				{
					"name" : "ADVANCED",
					"value" : "1"
				},
				{
					"name" : "HELPSTRING",
					"value" : "Path to a program."
				}
			],
			"type" : "FILEPATH",
			"value" : "CLANG_FORMAT_PROGRAM-NOTFOUND"
		},
		{
			"name" : "CLANG_TIDY_PROGRAM",
			"properties" : 
			[
				{
					"name" : "ADVANCED",
					"value" : "1"
				},
				{
					"name" : "HELPSTRING",
					"value" : "Path to a program."
				}
			],
			"type" : "FILEPATH",
			"value" : "CLANG_TIDY_PROGRAM-NOTFOUND"
		},
		{
			"name" : "CMAKE_ADDR2LINE",
			"properties" : 
			[
				{
					"name" : "ADVANCED",
					"value" : "1"
				},
				{
					"name" : "HELPSTRING",
					"value" : "Path to a program."
				}
			],
			"type" : "FILEPATH",
			"value" : "CMAKE_ADDR2LINE-NOTFOUND"
		},
		{
			"name" : "CMAKE_AR",
			"properties" : 
			[
				{
					"name" : "ADVANCED",
					"value" : "1"
				},
				{
					"name" : "HELPSTRING",
					"value" : "Path to a program."
				}
			],
			"type" : "FILEPATH",
			"value" : "/Applications/Xcode.app/Contents/Developer/Toolchains/XcodeDefault.xctoolchain/usr/bin/ar"
		},
		{
			"name" : "CMAKE_ARCHIVE_OUTPUT_DIRECTORY",
			"properties" : 
			[
				{
					"name" : "HELPSTRING",
					"value" : "Single Directory for all static libraries."
				}
			],
			"type" : "PATH",
			"value" : "/Users/brk/_private/repos/utils/Camel-Snake-Util/cmake-build-debug-system/lib"
		},
		{
			"name" : "CMAKE_BUILD_TYPE",
			"properties" : 
			[
				{
					"name" : "HELPSTRING",
					"value" : "Choose the type of build, options are: None Debug Release RelWithDebInfo MinSizeRel ..."
				}
			],
			"type" : "STRING",
			"value" : "Debug"
		},
		{
			"name" : "CMAKE_CACHEFILE_DIR",
			"properties" : 
			[
				{
					"name" : "HELPSTRING",
					"value" : "This is the directory where this CMakeCache.txt was created"
				}
			],
			"type" : "INTERNAL",
			"value" : "/Users/brk/_private/repos/utils/Camel-Snake-Util/cmake-build-debug-system"
		},
		{
			"name" : "CMAKE_CACHE_MAJOR_VERSION",
			"properties" : 
			[
				{
					"name" : "HELPSTRING",
					"value" : "Major version of cmake used to create the current loaded cache"
				}
			],
			"type" : "INTERNAL",
			"value" : "3"
		},
		{
			"name" : "CMAKE_CACHE_MINOR_VERSION",
			"properties" : 
			[
				{
					"name" : "HELPSTRING",
					"value" : "Minor version of cmake used to create the current loaded cache"
				}
			],
			"type" : "INTERNAL",
			"value" : "27"
		},
		{
			"name" : "CMAKE_CACHE_PATCH_VERSION",
			"properties" : 
			[
				{
					"name" : "HELPSTRING",
					"value" : "Patch version of cmake used to create the current loaded cache"
				}
			],
			"type" : "INTERNAL",
			"value" : "8"
		},
		{
			"name" : "CMAKE_COLOR_DIAGNOSTICS",
			"properties" : 
			[
				{
					"name" : "HELPSTRING",
					"value" : "Enable colored diagnostics throughout."
				}
			],
			"type" : "BOOL",
			"value" : "ON"
		},
		{
			"name" : "CMAKE_COLOR_MAKEFILE",
			"properties" : 
			[
				{
					"name" : "ADVANCED",
					"value" : "1"
				},
				{
					"name" : "HELPSTRING",
					"value" : ""
				}
			],
			"type" : "UNINITIALIZED",
			"value" : ""
		},
		{
			"name" : "CMAKE_COMMAND",
			"properties" : 
			[
				{
					"name" : "HELPSTRING",
					"value" : "Path to CMake executable."
				}
			],
			"type" : "INTERNAL",
			"value" : "/Users/brk/Applications/CLion.app/Contents/bin/cmake/mac/aarch64/bin/cmake"
		},
		{
			"name" : "CMAKE_CPACK_COMMAND",
			"properties" : 
			[
				{
					"name" : "HELPSTRING",
					"value" : "Path to cpack program executable."
				}
			],
			"type" : "INTERNAL",
			"value" : "/Users/brk/Applications/CLion.app/Contents/bin/cmake/mac/aarch64/bin/cpack"
		},
		{
			"name" : "CMAKE_CTEST_COMMAND",
			"properties" : 
			[
				{
					"name" : "HELPSTRING",
					"value" : "Path to ctest program executable."
				}
			],
			"type" : "INTERNAL",
			"value" : "/Users/brk/Applications/CLion.app/Contents/bin/cmake/mac/aarch64/bin/ctest"
		},
		{
			"name" : "CMAKE_CXX_COMPILER",
			"properties" : 
			[
				{
					"name" : "ADVANCED",
					"value" : "1"
				},
				{
					"name" : "HELPSTRING",
					"value" : "CXX compiler"
				}
			],
			"type" : "FILEPATH",
			"value" : "/Applications/Xcode.app/Contents/Developer/Toolchains/XcodeDefault.xctoolchain/usr/bin/c++"
		},
		{
			"name" : "CMAKE_CXX_EXTENSIONS",
			"properties" : 
			[
				{
					"name" : "HELPSTRING",
					"value" : "When C++ is enabled, this flag is passed to the compiler."
				}
			],
			"type" : "BOOL",
			"value" : "ON"
		},
		{
			"name" : "CMAKE_CXX_FLAGS",
			"properties" : 
			[
				{
					"name" : "ADVANCED",
					"value" : "1"
				},
				{
					"name" : "HELPSTRING",
					"value" : "Flags used by the CXX compiler during all build types."
				}
			],
			"type" : "STRING",
			"value" : ""
		},
		{
			"name" : "CMAKE_CXX_FLAGS_DEBUG",
			"properties" : 
			[
				{
					"name" : "ADVANCED",
					"value" : "1"
				},
				{
					"name" : "HELPSTRING",
					"value" : "Flags used by the CXX compiler during DEBUG builds."
				}
			],
			"type" : "STRING",
			"value" : "-g"
		},
		{
			"name" : "CMAKE_CXX_FLAGS_MINSIZEREL",
			"properties" : 
			[
				{
					"name" : "ADVANCED",
					"value" : "1"
				},
				{
					"name" : "HELPSTRING",
					"value" : "Flags used by the CXX compiler during MINSIZEREL builds."
				}
			],
			"type" : "STRING",
			"value" : "-Os -DNDEBUG"
		},
		{
			"name" : "CMAKE_CXX_FLAGS_RELEASE",
			"properties" : 
			[
				{
					"name" : "ADVANCED",
					"value" : "1"
				},
				{
					"name" : "HELPSTRING",
					"value" : "Flags used by the CXX compiler during RELEASE builds."
				}
			],
			"type" : "STRING",
			"value" : "-O3 -DNDEBUG"
		},
		{
			"name" : "CMAKE_CXX_FLAGS_RELWITHDEBINFO",
			"properties" : 
			[
				{
					"name" : "ADVANCED",
					"value" : "1"
				},
				{
					"name" : "HELPSTRING",
					"value" : "Flags used by the CXX compiler during RELWITHDEBINFO builds."
				}
			],
			"type" : "STRING",
			"value" : "-O2 -g -DNDEBUG"
		},
		{
			"name" : "CMAKE_CXX_STANDARD",
			"properties" : 
			[
				{
					"name" : "HELPSTRING",
					"value" : "The C++ standard whose features are requested."
				}
			],
			"type" : "STRING",
			"value" : "23"
		},
		{
			"name" : "CMAKE_CXX_STANDARD_REQUIRED",
			"properties" : 
			[
				{
					"name" : "HELPSTRING",
					"value" : "The C++ standard is required."
				}
			],
			"type" : "BOOL",
			"value" : "ON"
		},
		{
			"name" : "CMAKE_C_COMPILER",
			"properties" : 
			[
				{
					"name" : "ADVANCED",
					"value" : "1"
				},
				{
					"name" : "HELPSTRING",
					"value" : "C compiler"
				}
			],
			"type" : "FILEPATH",
			"value" : "/Applications/Xcode.app/Contents/Developer/Toolchains/XcodeDefault.xctoolchain/usr/bin/cc"
		},
		{
			"name" : "CMAKE_C_FLAGS",
			"properties" : 
			[
				{
					"name" : "ADVANCED",
					"value" : "1"
				},
				{
					"name" : "HELPSTRING",
					"value" : "Flags used by the C compiler during all build types."
				}
			],
			"type" : "STRING",
			"value" : ""
		},
		{
			"name" : "CMAKE_C_FLAGS_DEBUG",
			"properties" : 
			[
				{
					"name" : "ADVANCED",
					"value" : "1"
				},
				{
					"name" : "HELPSTRING",
					"value" : "Flags used by the C compiler during DEBUG builds."
				}
			],
			"type" : "STRING",
			"value" : "-g"
		},
		{
			"name" : "CMAKE_C_FLAGS_MINSIZEREL",
			"properties" : 
			[
				{
					"name" : "ADVANCED",
					"value" : "1"
				},
				{
					"name" : "HELPSTRING",
					"value" : "Flags used by the C compiler during MINSIZEREL builds."
				}
			],
			"type" : "STRING",
			"value" : "-Os -DNDEBUG"
		},
		{
			"name" : "CMAKE_C_FLAGS_RELEASE",
			"properties" : 
			[
				{
					"name" : "ADVANCED",
					"value" : "1"
				},
				{
					"name" : "HELPSTRING",
					"value" : "Flags used by the C compiler during RELEASE builds."
				}
			],
			"type" : "STRING",
			"value" : "-O3 -DNDEBUG"
		},
		{
			"name" : "CMAKE_C_FLAGS_RELWITHDEBINFO",
			"properties" : 
			[
				{
					"name" : "ADVANCED",
					"value" : "1"
				},
				{
					"name" : "HELPSTRING",
					"value" : "Flags used by the C compiler during RELWITHDEBINFO builds."
				}
			],
			"type" : "STRING",
			"value" : "-O2 -g -DNDEBUG"
		},
		{
			"name" : "CMAKE_DLLTOOL",
			"properties" : 
			[
				{
					"name" : "ADVANCED",
					"value" : "1"
				},
				{
					"name" : "HELPSTRING",
					"value" : "Path to a program."
				}
			],
			"type" : "FILEPATH",
			"value" : "CMAKE_DLLTOOL-NOTFOUND"
		},
		{
			"name" : "CMAKE_EXECUTABLE_FORMAT",
			"properties" : 
			[
				{
					"name" : "HELPSTRING",
					"value" : "Executable file format"
				}
			],
			"type" : "INTERNAL",
			"value" : "MACHO"
		},
		{
			"name" : "CMAKE_EXE_LINKER_FLAGS",
			"properties" : 
			[
				{
					"name" : "ADVANCED",
					"value" : "1"
				},
				{
					"name" : "HELPSTRING",
					"value" : "Flags used by the linker during all build types."
				}
			],
			"type" : "STRING",
			"value" : ""
		},
		{
			"name" : "CMAKE_EXE_LINKER_FLAGS_DEBUG",
			"properties" : 
			[
				{
					"name" : "ADVANCED",
					"value" : "1"
				},
				{
					"name" : "HELPSTRING",
					"value" : "Flags used by the linker during DEBUG builds."
				}
			],
			"type" : "STRING",
			"value" : ""
		},
		{
			"name" : "CMAKE_EXE_LINKER_FLAGS_MINSIZEREL",
			"properties" : 
			[
				{
					"name" : "ADVANCED",
					"value" : "1"
				},
				{
					"name" : "HELPSTRING",
					"value" : "Flags used by the linker during MINSIZEREL builds."
				}
			],
			"type" : "STRING",
			"value" : ""
		},
		{
			"name" : "CMAKE_EXE_LINKER_FLAGS_RELEASE",
			"properties" : 
			[
				{
					"name" : "ADVANCED",
					"value" : "1"
				},
				{
					"name" : "HELPSTRING",
					"value" : "Flags used by the linker during RELEASE builds."
				}
			],
			"type" : "STRING",
			"value" : ""
		},
		{
			"name" : "CMAKE_EXE_LINKER_FLAGS_RELWITHDEBINFO",
			"properties" : 
			[
				{
					"name" : "ADVANCED",
					"value" : "1"
				},
				{
					"name" : "HELPSTRING",
					"value" : "Flags used by the linker during RELWITHDEBINFO builds."
				}
			],
			"type" : "STRING",
			"value" : ""
		},
		{
			"name" : "CMAKE_EXPORT_COMPILE_COMMANDS",
			"properties" : 
			[
				{
					"name" : "ADVANCED",
					"value" : "1"
				},
				{
					"name" : "HELPSTRING",
					"value" : "Enable/Disable output of compile commands during generation."
				}
			],
			"type" : "BOOL",
			"value" : ""
		},
		{
			"name" : "CMAKE_EXTRA_GENERATOR",
			"properties" : 
			[
				{
					"name" : "HELPSTRING",
					"value" : "Name of external makefile project generator."
				}
			],
			"type" : "INTERNAL",
			"value" : ""
		},
		{
			"name" : "CMAKE_FIND_PACKAGE_REDIRECTS_DIR",
			"properties" : 
			[
				{
					"name" : "HELPSTRING",
					"value" : "Value Computed by CMake."
				}
			],
			"type" : "STATIC",
			"value" : "/Users/brk/_private/repos/utils/Camel-Snake-Util/cmake-build-debug-system/CMakeFiles/pkgRedirects"
		},
		{
			"name" : "CMAKE_GENERATOR",
			"properties" : 
			[
				{
					"name" : "HELPSTRING",
					"value" : "Name of generator."
				}
			],
			"type" : "INTERNAL",
			"value" : "Unix Makefiles"
		},
		{
			"name" : "CMAKE_GENERATOR_INSTANCE",
			"properties" : 
			[
				{
					"name" : "HELPSTRING",
					"value" : "Generator instance identifier."
				}
			],
			"type" : "INTERNAL",
			"value" : ""
		},
		{
			"name" : "CMAKE_GENERATOR_PLATFORM",
			"properties" : 
			[
				{
					"name" : "HELPSTRING",
					"value" : "Name of generator platform."
				}
			],
			"type" : "INTERNAL",
			"value" : ""
		},
		{
			"name" : "CMAKE_GENERATOR_TOOLSET",
			"properties" : 
			[
				{
					"name" : "HELPSTRING",
					"value" : "Name of generator toolset."
				}
			],
			"type" : "INTERNAL",
			"value" : ""
		},
		{
			"name" : "CMAKE_HAVE_LIBC_PTHREAD",
			"properties" : 
			[
				{
					"name" : "HELPSTRING",
					"value" : "Test CMAKE_HAVE_LIBC_PTHREAD"
				}
			],
			"type" : "INTERNAL",
			"value" : "1"
		},
		{
			"name" : "CMAKE_HOME_DIRECTORY",
			"properties" : 
			[
				{
					"name" : "HELPSTRING",
					"value" : "Source directory with the top level CMakeLists.txt file for this project"
				}
			],
			"type" : "INTERNAL",
			"value" : "/Users/brk/_private/repos/utils/Camel-Snake-Util"
		},
		{
			"name" : "CMAKE_INSTALL_BINDIR",
			"properties" : 
			[
				{
					"name" : "ADVANCED",
					"value" : "1"
				},
				{
					"name" : "HELPSTRING",
					"value" : "User executables (bin)"
				}
			],
			"type" : "PATH",
			"value" : "bin"
		},
		{
			"name" : "CMAKE_INSTALL_DATADIR",
			"properties" : 
			[
				{
					"name" : "ADVANCED",
					"value" : "1"
				},
				{
					"name" : "HELPSTRING",
					"value" : "Read-only architecture-independent data (DATAROOTDIR)"
				}
			],
			"type" : "PATH",
			"value" : ""
		},
		{
			"name" : "CMAKE_INSTALL_DATAROOTDIR",
			"properties" : 
			[
				{
					"name" : "ADVANCED",
					"value" : "1"
				},
				{
					"name" : "HELPSTRING",
					"value" : "Read-only architecture-independent data root (share)"
				}
			],
			"type" : "PATH",
			"value" : "share"
		},
		{
			"name" : "CMAKE_INSTALL_DOCDIR",
			"properties" : 
			[
				{
					"name" : "ADVANCED",
					"value" : "1"
				},
				{
					"name" : "HELPSTRING",
					"value" : "Documentation root (DATAROOTDIR/doc/PROJECT_NAME)"
				}
			],
			"type" : "PATH",
			"value" : ""
		},
		{
			"name" : "CMAKE_INSTALL_INCLUDEDIR",
			"properties" : 
			[
				{
					"name" : "ADVANCED",
					"value" : "1"
				},
				{
					"name" : "HELPSTRING",
					"value" : "C header files (include)"
				}
			],
			"type" : "PATH",
			"value" : "include"
		},
		{
			"name" : "CMAKE_INSTALL_INFODIR",
			"properties" : 
			[
				{
					"name" : "ADVANCED",
					"value" : "1"
				},
				{
					"name" : "HELPSTRING",
					"value" : "Info documentation (DATAROOTDIR/info)"
				}
			],
			"type" : "PATH",
			"value" : ""
		},
		{
			"name" : "CMAKE_INSTALL_LIBDIR",
			"properties" : 
			[
				{
					"name" : "ADVANCED",
					"value" : "1"
				},
				{
					"name" : "HELPSTRING",
					"value" : "Object code libraries (lib)"
				}
			],
			"type" : "PATH",
			"value" : "lib"
		},
		{
			"name" : "CMAKE_INSTALL_LIBEXECDIR",
			"properties" : 
			[
				{
					"name" : "ADVANCED",
					"value" : "1"
				},
				{
					"name" : "HELPSTRING",
					"value" : "Program executables (libexec)"
				}
			],
			"type" : "PATH",
			"value" : "libexec"
		},
		{
			"name" : "CMAKE_INSTALL_LOCALEDIR",
			"properties" : 
			[
				{
					"name" : "ADVANCED",
					"value" : "1"
				},
				{
					"name" : "HELPSTRING",
					"value" : "Locale-dependent data (DATAROOTDIR/locale)"
				}
			],
			"type" : "PATH",
			"value" : ""
		},
		{
			"name" : "CMAKE_INSTALL_LOCALSTATEDIR",
			"properties" : 
			[
				{
					"name" : "ADVANCED",
					"value" : "1"
				},
				{
					"name" : "HELPSTRING",
					"value" : "Modifiable single-machine data (var)"
				}
			],
			"type" : "PATH",
			"value" : "var"
		},
		{
			"name" : "CMAKE_INSTALL_MANDIR",
			"properties" : 
			[
				{
					"name" : "ADVANCED",
					"value" : "1"
				},
				{
					"name" : "HELPSTRING",
					"value" : "Man documentation (DATAROOTDIR/man)"
				}
			],
			"type" : "PATH",
			"value" : ""
		},
		{
			"name" : "CMAKE_INSTALL_NAME_TOOL",
			"properties" : 
			[
				{
					"name" : "ADVANCED",
					"value" : "1"
				},
				{
					"name" : "HELPSTRING",
					"value" : "Path to a program."
				}
			],
			"type" : "FILEPATH",
			"value" : "/usr/bin/install_name_tool"
		},
		{
			"name" : "CMAKE_INSTALL_OLDINCLUDEDIR",
			"properties" : 
			[
				{
					"name" : "ADVANCED",
					"value" : "1"
				},
				{
					"name" : "HELPSTRING",
					"value" : "C header files for non-gcc (/usr/include)"
				}
			],
			"type" : "PATH",
			"value" : "/usr/include"
		},
		{
			"name" : "CMAKE_INSTALL_PREFIX",
			"properties" : 
			[
				{
					"name" : "HELPSTRING",
					"value" : "Install path prefix, prepended onto install directories."
				}
			],
			"type" : "PATH",
			"value" : "/usr/local"
		},
		{
			"name" : "CMAKE_INSTALL_RUNSTATEDIR",
			"properties" : 
			[
				{
					"name" : "ADVANCED",
					"value" : "1"
				},
				{
					"name" : "HELPSTRING",
					"value" : "Run-time variable data (LOCALSTATEDIR/run)"
				}
			],
			"type" : "PATH",
			"value" : ""
		},
		{
			"name" : "CMAKE_INSTALL_SBINDIR",
			"properties" : 
			[
				{
					"name" : "ADVANCED",
					"value" : "1"
				},
				{
					"name" : "HELPSTRING",
					"value" : "System admin executables (sbin)"
				}
			],
			"type" : "PATH",
			"value" : "sbin"
		},
		{
			"name" : "CMAKE_INSTALL_SHAREDSTATEDIR",
			"properties" : 
			[
				{
					"name" : "ADVANCED",
					"value" : "1"
				},
				{
					"name" : "HELPSTRING",
					"value" : "Modifiable architecture-independent data (com)"
				}
			],
			"type" : "PATH",
			"value" : "com"
		},
		{
			"name" : "CMAKE_INSTALL_SYSCONFDIR",
			"properties" : 
			[
				{
					"name" : "ADVANCED",
					"value" : "1"
				},
				{
					"name" : "HELPSTRING",
					"value" : "Read-only single-machine data (etc)"
				}
			],
			"type" : "PATH",
			"value" : "etc"
		},
		{
			"name" : "CMAKE_LIBRARY_OUTPUT_DIRECTORY",
			"properties" : 
			[
				{
					"name" : "HELPSTRING",
					"value" : "Single Directory for all Libraries"
				}
			],
			"type" : "PATH",
			"value" : "/Users/brk/_private/repos/utils/Camel-Snake-Util/cmake-build-debug-system/bin"
		},
		{
			"name" : "CMAKE_LINKER",
			"properties" : 
			[
				{
					"name" : "ADVANCED",
					"value" : "1"
				},
				{
					"name" : "HELPSTRING",
					"value" : "Path to a program."
				}
			],
			"type" : "FILEPATH",
			"value" : "/Applications/Xcode.app/Contents/Developer/Toolchains/XcodeDefault.xctoolchain/usr/bin/ld"
		},
		{
			"name" : "CMAKE_MAKE_PROGRAM",
			"properties" : 
			[
				{
					"name" : "ADVANCED",
					"value" : "1"
				},
				{
					"name" : "HELPSTRING",
					"value" : "Path to a program."
				}
			],
			"type" : "FILEPATH",
			"value" : "/usr/bin/make"
		},
		{
			"name" : "CMAKE_MODULE_LINKER_FLAGS",
			"properties" : 
			[
				{
					"name" : "ADVANCED",
					"value" : "1"
				},
				{
					"name" : "HELPSTRING",
					"value" : "Flags used by the linker during the creation of modules during all build types."
				}
			],
			"type" : "STRING",
			"value" : ""
		},
		{
			"name" : "CMAKE_MODULE_LINKER_FLAGS_DEBUG",
			"properties" : 
			[
				{
					"name" : "ADVANCED",
					"value" : "1"
				},
				{
					"name" : "HELPSTRING",
					"value" : "Flags used by the linker during the creation of modules during DEBUG builds."
				}
			],
			"type" : "STRING",
			"value" : ""
		},
		{
			"name" : "CMAKE_MODULE_LINKER_FLAGS_MINSIZEREL",
			"properties" : 
			[
				{
					"name" : "ADVANCED",
					"value" : "1"
				},
				{
					"name" : "HELPSTRING",
					"value" : "Flags used by the linker during the creation of modules during MINSIZEREL builds."
				}
			],
			"type" : "STRING",
			"value" : ""
		},
		{
			"name" : "CMAKE_MODULE_LINKER_FLAGS_RELEASE",
			"properties" : 
			[
				{
					"name" : "ADVANCED",
					"value" : "1"
				},
				{
					"name" : "HELPSTRING",
					"value" : "Flags used by the linker during the creation of modules during RELEASE builds."
				}
			],
			"type" : "STRING",
			"value" : ""
		},
		{
			"name" : "CMAKE_MODULE_LINKER_FLAGS_RELWITHDEBINFO",
			"properties" : 
			[
				{
					"name" : "ADVANCED",
					"value" : "1"
				},
				{
					"name" : "HELPSTRING",
					"value" : "Flags used by the linker during the creation of modules during RELWITHDEBINFO builds."
				}
			],
			"type" : "STRING",
			"value" : ""
		},
		{
			"name" : "CMAKE_NM",
			"properties" : 
			[
				{
					"name" : "ADVANCED",
					"value" : "1"
				},
				{
					"name" : "HELPSTRING",
					"value" : "Path to a program."
				}
			],
			"type" : "FILEPATH",
			"value" : "/Applications/Xcode.app/Contents/Developer/Toolchains/XcodeDefault.xctoolchain/usr/bin/nm"
		},
		{
			"name" : "CMAKE_NUMBER_OF_MAKEFILES",
			"properties" : 
			[
				{
					"name" : "HELPSTRING",
					"value" : "number of local generators"
				}
			],
			"type" : "INTERNAL",
			"value" : "23"
		},
		{
			"name" : "CMAKE_OBJCOPY",
			"properties" : 
			[
				{
					"name" : "ADVANCED",
					"value" : "1"
				},
				{
					"name" : "HELPSTRING",
					"value" : "Path to a program."
				}
			],
			"type" : "FILEPATH",
			"value" : "CMAKE_OBJCOPY-NOTFOUND"
		},
		{
			"name" : "CMAKE_OBJCXX_COMPILER",
			"properties" : 
			[
				{
					"name" : "ADVANCED",
					"value" : "1"
				},
				{
					"name" : "HELPSTRING",
					"value" : "OBJCXX compiler"
				}
			],
			"type" : "FILEPATH",
			"value" : "/Applications/Xcode.app/Contents/Developer/Toolchains/XcodeDefault.xctoolchain/usr/bin/c++"
		},
		{
			"name" : "CMAKE_OBJCXX_FLAGS",
			"properties" : 
			[
				{
					"name" : "ADVANCED",
					"value" : "1"
				},
				{
					"name" : "HELPSTRING",
					"value" : "Flags used by the Objective-C++ compiler during all build types."
				}
			],
			"type" : "STRING",
			"value" : ""
		},
		{
			"name" : "CMAKE_OBJCXX_FLAGS_DEBUG",
			"properties" : 
			[
				{
					"name" : "ADVANCED",
					"value" : "1"
				},
				{
					"name" : "HELPSTRING",
					"value" : "Flags used by the Objective-C++ compiler during DEBUG builds."
				}
			],
			"type" : "STRING",
			"value" : "-g"
		},
		{
			"name" : "CMAKE_OBJCXX_FLAGS_MINSIZEREL",
			"properties" : 
			[
				{
					"name" : "ADVANCED",
					"value" : "1"
				},
				{
					"name" : "HELPSTRING",
					"value" : "Flags used by the Objective-C++ compiler during MINSIZEREL builds."
				}
			],
			"type" : "STRING",
			"value" : "-Os -DNDEBUG"
		},
		{
			"name" : "CMAKE_OBJCXX_FLAGS_RELEASE",
			"properties" : 
			[
				{
					"name" : "ADVANCED",
					"value" : "1"
				},
				{
					"name" : "HELPSTRING",
					"value" : "Flags used by the Objective-C++ compiler during RELEASE builds."
				}
			],
			"type" : "STRING",
			"value" : "-O3 -DNDEBUG"
		},
		{
			"name" : "CMAKE_OBJCXX_FLAGS_RELWITHDEBINFO",
			"properties" : 
			[
				{
					"name" : "ADVANCED",
					"value" : "1"
				},
				{
					"name" : "HELPSTRING",
					"value" : "Flags used by the Objective-C++ compiler during RELWITHDEBINFO builds."
				}
			],
			"type" : "STRING",
			"value" : "-O2 -g -DNDEBUG"
		},
		{
			"name" : "CMAKE_OBJC_COMPILER",
			"properties" : 
			[
				{
					"name" : "ADVANCED",
					"value" : "1"
				},
				{
					"name" : "HELPSTRING",
					"value" : "OBJC compiler"
				}
			],
			"type" : "FILEPATH",
			"value" : "/Applications/Xcode.app/Contents/Developer/Toolchains/XcodeDefault.xctoolchain/usr/bin/cc"
		},
		{
			"name" : "CMAKE_OBJC_FLAGS",
			"properties" : 
			[
				{
					"name" : "ADVANCED",
					"value" : "1"
				},
				{
					"name" : "HELPSTRING",
					"value" : "Flags used by the Objective-C compiler during all build types."
				}
			],
			"type" : "STRING",
			"value" : ""
		},
		{
			"name" : "CMAKE_OBJC_FLAGS_DEBUG",
			"properties" : 
			[
				{
					"name" : "ADVANCED",
					"value" : "1"
				},
				{
					"name" : "HELPSTRING",
					"value" : "Flags used by the Objective-C compiler during DEBUG builds."
				}
			],
			"type" : "STRING",
			"value" : "-g"
		},
		{
			"name" : "CMAKE_OBJC_FLAGS_MINSIZEREL",
			"properties" : 
			[
				{
					"name" : "ADVANCED",
					"value" : "1"
				},
				{
					"name" : "HELPSTRING",
					"value" : "Flags used by the Objective-C compiler during MINSIZEREL builds."
				}
			],
			"type" : "STRING",
			"value" : "-Os -DNDEBUG"
		},
		{
			"name" : "CMAKE_OBJC_FLAGS_RELEASE",
			"properties" : 
			[
				{
					"name" : "ADVANCED",
					"value" : "1"
				},
				{
					"name" : "HELPSTRING",
					"value" : "Flags used by the Objective-C compiler during RELEASE builds."
				}
			],
			"type" : "STRING",
			"value" : "-O3 -DNDEBUG"
		},
		{
			"name" : "CMAKE_OBJC_FLAGS_RELWITHDEBINFO",
			"properties" : 
			[
				{
					"name" : "ADVANCED",
					"value" : "1"
				},
				{
					"name" : "HELPSTRING",
					"value" : "Flags used by the Objective-C compiler during RELWITHDEBINFO builds."
				}
			],
			"type" : "STRING",
			"value" : "-O2 -g -DNDEBUG"
		},
		{
			"name" : "CMAKE_OBJDUMP",
			"properties" : 
			[
				{
					"name" : "ADVANCED",
					"value" : "1"
				},
				{
					"name" : "HELPSTRING",
					"value" : "Path to a program."
				}
			],
			"type" : "FILEPATH",
			"value" : "/Applications/Xcode.app/Contents/Developer/Toolchains/XcodeDefault.xctoolchain/usr/bin/objdump"
		},
		{
			"name" : "CMAKE_OSX_ARCHITECTURES",
			"properties" : 
			[
				{
					"name" : "HELPSTRING",
					"value" : "Build architectures for OSX"
				}
			],
			"type" : "STRING",
			"value" : ""
		},
		{
			"name" : "CMAKE_OSX_DEPLOYMENT_TARGET",
			"properties" : 
			[
				{
					"name" : "HELPSTRING",
					"value" : "Minimum OS X version to target for deployment (at runtime); newer APIs weak linked. Set to empty string for default value."
				}
			],
			"type" : "STRING",
			"value" : ""
		},
		{
			"name" : "CMAKE_OSX_SYSROOT",
			"properties" : 
			[
				{
					"name" : "HELPSTRING",
					"value" : "The product will be built against the headers and libraries located inside the indicated SDK."
				}
			],
			"type" : "PATH",
			"value" : "/Applications/Xcode.app/Contents/Developer/Platforms/MacOSX.platform/Developer/SDKs/MacOSX14.4.sdk"
		},
		{
			"name" : "CMAKE_PLATFORM_INFO_INITIALIZED",
			"properties" : 
			[
				{
					"name" : "HELPSTRING",
					"value" : "Platform information initialized"
				}
			],
			"type" : "INTERNAL",
			"value" : "1"
		},
		{
			"name" : "CMAKE_PROJECT_DESCRIPTION",
			"properties" : 
			[
				{
					"name" : "HELPSTRING",
					"value" : "Value Computed by CMake"
				}
			],
			"type" : "STATIC",
			"value" : ""
		},
		{
			"name" : "CMAKE_PROJECT_HOMEPAGE_URL",
			"properties" : 
			[
				{
					"name" : "HELPSTRING",
					"value" : "Value Computed by CMake"
				}
			],
			"type" : "STATIC",
			"value" : ""
		},
		{
			"name" : "CMAKE_PROJECT_NAME",
			"properties" : 
			[
				{
					"name" : "HELPSTRING",
					"value" : "Value Computed by CMake"
				}
			],
			"type" : "STATIC",
			"value" : "CamelSnakeUtil"
		},
		{
			"name" : "CMAKE_PROJECT_VERSION",
			"properties" : 
			[
				{
					"name" : "HELPSTRING",
					"value" : "Value Computed by CMake"
				}
			],
			"type" : "STATIC",
			"value" : "0.12.0"
		},
		{
			"name" : "CMAKE_PROJECT_VERSION_MAJOR",
			"properties" : 
			[
				{
					"name" : "HELPSTRING",
					"value" : "Value Computed by CMake"
				}
			],
			"type" : "STATIC",
			"value" : "0"
		},
		{
			"name" : "CMAKE_PROJECT_VERSION_MINOR",
			"properties" : 
			[
				{
					"name" : "HELPSTRING",
					"value" : "Value Computed by CMake"
				}
			],
			"type" : "STATIC",
			"value" : "12"
		},
		{
			"name" : "CMAKE_PROJECT_VERSION_PATCH",
			"properties" : 
			[
				{
					"name" : "HELPSTRING",
					"value" : "Value Computed by CMake"
				}
			],
			"type" : "STATIC",
			"value" : "0"
		},
		{
			"name" : "CMAKE_PROJECT_VERSION_TWEAK",
			"properties" : 
			[
				{
					"name" : "HELPSTRING",
					"value" : "Value Computed by CMake"
				}
			],
			"type" : "STATIC",
			"value" : ""
		},
		{
			"name" : "CMAKE_RANLIB",
			"properties" : 
			[
				{
					"name" : "ADVANCED",
					"value" : "1"
				},
				{
					"name" : "HELPSTRING",
					"value" : "Path to a program."
				}
			],
			"type" : "FILEPATH",
			"value" : "/Applications/Xcode.app/Contents/Developer/Toolchains/XcodeDefault.xctoolchain/usr/bin/ranlib"
		},
		{
			"name" : "CMAKE_READELF",
			"properties" : 
			[
				{
					"name" : "ADVANCED",
					"value" : "1"
				},
				{
					"name" : "HELPSTRING",
					"value" : "Path to a program."
				}
			],
			"type" : "FILEPATH",
			"value" : "CMAKE_READELF-NOTFOUND"
		},
		{
			"name" : "CMAKE_ROOT",
			"properties" : 
			[
				{
					"name" : "HELPSTRING",
					"value" : "Path to CMake installation."
				}
			],
			"type" : "INTERNAL",
			"value" : "/Users/brk/Applications/CLion.app/Contents/bin/cmake/mac/aarch64/share/cmake-3.27"
		},
		{
			"name" : "CMAKE_RUNTIME_OUTPUT_DIRECTORY",
			"properties" : 
			[
				{
					"name" : "HELPSTRING",
					"value" : "Single Directory for all Executables."
				}
			],
			"type" : "PATH",
			"value" : "/Users/brk/_private/repos/utils/Camel-Snake-Util/cmake-build-debug-system/bin"
		},
		{
			"name" : "CMAKE_SHARED_LINKER_FLAGS",
			"properties" : 
			[
				{
					"name" : "ADVANCED",
					"value" : "1"
				},
				{
					"name" : "HELPSTRING",
					"value" : "Flags used by the linker during the creation of shared libraries during all build types."
				}
			],
			"type" : "STRING",
			"value" : ""
		},
		{
			"name" : "CMAKE_SHARED_LINKER_FLAGS_DEBUG",
			"properties" : 
			[
				{
					"name" : "ADVANCED",
					"value" : "1"
				},
				{
					"name" : "HELPSTRING",
					"value" : "Flags used by the linker during the creation of shared libraries during DEBUG builds."
				}
			],
			"type" : "STRING",
			"value" : ""
		},
		{
			"name" : "CMAKE_SHARED_LINKER_FLAGS_MINSIZEREL",
			"properties" : 
			[
				{
					"name" : "ADVANCED",
					"value" : "1"
				},
				{
					"name" : "HELPSTRING",
					"value" : "Flags used by the linker during the creation of shared libraries during MINSIZEREL builds."
				}
			],
			"type" : "STRING",
			"value" : ""
		},
		{
			"name" : "CMAKE_SHARED_LINKER_FLAGS_RELEASE",
			"properties" : 
			[
				{
					"name" : "ADVANCED",
					"value" : "1"
				},
				{
					"name" : "HELPSTRING",
					"value" : "Flags used by the linker during the creation of shared libraries during RELEASE builds."
				}
			],
			"type" : "STRING",
			"value" : ""
		},
		{
			"name" : "CMAKE_SHARED_LINKER_FLAGS_RELWITHDEBINFO",
			"properties" : 
			[
				{
					"name" : "ADVANCED",
					"value" : "1"
				},
				{
					"name" : "HELPSTRING",
					"value" : "Flags used by the linker during the creation of shared libraries during RELWITHDEBINFO builds."
				}
			],
			"type" : "STRING",
			"value" : ""
		},
		{
			"name" : "CMAKE_SKIP_INSTALL_RPATH",
			"properties" : 
			[
				{
					"name" : "ADVANCED",
					"value" : "1"
				},
				{
					"name" : "HELPSTRING",
					"value" : "If set, runtime paths are not added when installing shared libraries, but are added when building."
				}
			],
			"type" : "BOOL",
			"value" : "NO"
		},
		{
			"name" : "CMAKE_SKIP_RPATH",
			"properties" : 
			[
				{
					"name" : "ADVANCED",
					"value" : "1"
				},
				{
					"name" : "HELPSTRING",
					"value" : "If set, runtime paths are not added when using shared libraries."
				}
			],
			"type" : "BOOL",
			"value" : "NO"
		},
		{
			"name" : "CMAKE_STATIC_LINKER_FLAGS",
			"properties" : 
			[
				{
					"name" : "ADVANCED",
					"value" : "1"
				},
				{
					"name" : "HELPSTRING",
					"value" : "Flags used by the linker during the creation of static libraries during all build types."
				}
			],
			"type" : "STRING",
			"value" : ""
		},
		{
			"name" : "CMAKE_STATIC_LINKER_FLAGS_DEBUG",
			"properties" : 
			[
				{
					"name" : "ADVANCED",
					"value" : "1"
				},
				{
					"name" : "HELPSTRING",
					"value" : "Flags used by the linker during the creation of static libraries during DEBUG builds."
				}
			],
			"type" : "STRING",
			"value" : ""
		},
		{
			"name" : "CMAKE_STATIC_LINKER_FLAGS_MINSIZEREL",
			"properties" : 
			[
				{
					"name" : "ADVANCED",
					"value" : "1"
				},
				{
					"name" : "HELPSTRING",
					"value" : "Flags used by the linker during the creation of static libraries during MINSIZEREL builds."
				}
			],
			"type" : "STRING",
			"value" : ""
		},
		{
			"name" : "CMAKE_STATIC_LINKER_FLAGS_RELEASE",
			"properties" : 
			[
				{
					"name" : "ADVANCED",
					"value" : "1"
				},
				{
					"name" : "HELPSTRING",
					"value" : "Flags used by the linker during the creation of static libraries during RELEASE builds."
				}
			],
			"type" : "STRING",
			"value" : ""
		},
		{
			"name" : "CMAKE_STATIC_LINKER_FLAGS_RELWITHDEBINFO",
			"properties" : 
			[
				{
					"name" : "ADVANCED",
					"value" : "1"
				},
				{
					"name" : "HELPSTRING",
					"value" : "Flags used by the linker during the creation of static libraries during RELWITHDEBINFO builds."
				}
			],
			"type" : "STRING",
			"value" : ""
		},
		{
			"name" : "CMAKE_STRIP",
			"properties" : 
			[
				{
					"name" : "ADVANCED",
					"value" : "1"
				},
				{
					"name" : "HELPSTRING",
					"value" : "Path to a program."
				}
			],
			"type" : "FILEPATH",
			"value" : "/Applications/Xcode.app/Contents/Developer/Toolchains/XcodeDefault.xctoolchain/usr/bin/strip"
		},
		{
			"name" : "CMAKE_TAPI",
			"properties" : 
			[
				{
					"name" : "ADVANCED",
					"value" : "1"
				},
				{
					"name" : "HELPSTRING",
					"value" : "Path to a program."
				}
			],
			"type" : "FILEPATH",
			"value" : "/Applications/Xcode.app/Contents/Developer/Toolchains/XcodeDefault.xctoolchain/usr/bin/tapi"
		},
		{
			"name" : "CMAKE_UNAME",
			"properties" : 
			[
				{
					"name" : "HELPSTRING",
					"value" : "uname command"
				}
			],
			"type" : "INTERNAL",
			"value" : "/usr/bin/uname"
		},
		{
			"name" : "CMAKE_VERBOSE_MAKEFILE",
			"properties" : 
			[
				{
					"name" : "ADVANCED",
					"value" : "1"
				},
				{
					"name" : "HELPSTRING",
					"value" : "If this value is on, makefiles will be generated without the .SILENT directive, and all commands will be echoed to the console during the make.  This is useful for debugging only. With Visual Studio IDE projects all commands are done without /nologo."
				}
			],
			"type" : "BOOL",
			"value" : "FALSE"
		},
		{
			"name" : "COCOA_LIBRARY",
			"properties" : 
			[
				{
					"name" : "HELPSTRING",
					"value" : "Path to a library."
				}
			],
			"type" : "FILEPATH",
			"value" : "/Applications/Xcode.app/Contents/Developer/Platforms/MacOSX.platform/Developer/SDKs/MacOSX14.4.sdk/System/Library/Frameworks/Cocoa.framework"
		},
		{
			"name" : "CPACK_SOURCE_RPM",
			"properties" : 
			[
				{
					"name" : "ADVANCED",
					"value" : "1"
				},
				{
					"name" : "HELPSTRING",
					"value" : "Enable to build RPM source packages"
				}
			],
			"type" : "BOOL",
			"value" : "OFF"
		},
		{
			"name" : "CPACK_SOURCE_TBZ2",
			"properties" : 
			[
				{
					"name" : "ADVANCED",
					"value" : "1"
				},
				{
					"name" : "HELPSTRING",
					"value" : "Enable to build TBZ2 source packages"
				}
			],
			"type" : "BOOL",
			"value" : "ON"
		},
		{
			"name" : "CPACK_SOURCE_TGZ",
			"properties" : 
			[
				{
					"name" : "ADVANCED",
					"value" : "1"
				},
				{
					"name" : "HELPSTRING",
					"value" : "Enable to build TGZ source packages"
				}
			],
			"type" : "BOOL",
			"value" : "ON"
		},
		{
			"name" : "CPACK_SOURCE_TXZ",
			"properties" : 
			[
				{
					"name" : "ADVANCED",
					"value" : "1"
				},
				{
					"name" : "HELPSTRING",
					"value" : "Enable to build TXZ source packages"
				}
			],
			"type" : "BOOL",
			"value" : "ON"
		},
		{
			"name" : "CPACK_SOURCE_TZ",
			"properties" : 
			[
				{
					"name" : "ADVANCED",
					"value" : "1"
				},
				{
					"name" : "HELPSTRING",
					"value" : "Enable to build TZ source packages"
				}
			],
			"type" : "BOOL",
			"value" : "ON"
		},
		{
			"name" : "CPACK_SOURCE_ZIP",
			"properties" : 
			[
				{
					"name" : "ADVANCED",
					"value" : "1"
				},
				{
					"name" : "HELPSTRING",
					"value" : "Enable to build ZIP source packages"
				}
			],
			"type" : "BOOL",
			"value" : "OFF"
		},
		{
			"name" : "CamelSnakeUtil_BINARY_DIR",
			"properties" : 
			[
				{
					"name" : "HELPSTRING",
					"value" : "Value Computed by CMake"
				}
			],
			"type" : "STATIC",
			"value" : "/Users/brk/_private/repos/utils/Camel-Snake-Util/cmake-build-debug-system"
		},
		{
			"name" : "CamelSnakeUtil_IS_TOP_LEVEL",
			"properties" : 
			[
				{
					"name" : "HELPSTRING",
					"value" : "Value Computed by CMake"
				}
			],
			"type" : "STATIC",
			"value" : "ON"
		},
		{
			"name" : "CamelSnakeUtil_SOURCE_DIR",
			"properties" : 
			[
				{
					"name" : "HELPSTRING",
					"value" : "Value Computed by CMake"
				}
			],
			"type" : "STATIC",
			"value" : "/Users/brk/_private/repos/utils/Camel-Snake-Util"
		},
		{
			"name" : "DVIPDF_CONVERTER",
			"properties" : 
			[
				{
					"name" : "ADVANCED",
					"value" : "1"
				},
				{
					"name" : "HELPSTRING",
					"value" : "Path to a program."
				}
			],
			"type" : "FILEPATH",
			"value" : "DVIPDF_CONVERTER-NOTFOUND"
		},
		{
			"name" : "DVIPS_CONVERTER",
			"properties" : 
			[
				{
					"name" : "ADVANCED",
					"value" : "1"
				},
				{
					"name" : "HELPSTRING",
					"value" : "Path to a program."
				}
			],
			"type" : "FILEPATH",
			"value" : "DVIPS_CONVERTER-NOTFOUND"
		},
		{
			"name" : "FIND_PACKAGE_MESSAGE_DETAILS_Git",
			"properties" : 
			[
				{
					"name" : "HELPSTRING",
					"value" : "Details about finding Git"
				}
			],
			"type" : "INTERNAL",
			"value" : "[/usr/bin/git][v2.39.3 (Apple Git-146)()]"
		},
		{
			"name" : "FIND_PACKAGE_MESSAGE_DETAILS_Python3",
			"properties" : 
			[
				{
					"name" : "HELPSTRING",
					"value" : "Details about finding Python3"
				}
			],
			"type" : "INTERNAL",
			"value" : "[/opt/homebrew/bin/python3][cfound components:  Interpreter ][v3.12.2()]"
		},
		{
			"name" : "FIND_PACKAGE_MESSAGE_DETAILS_Threads",
			"properties" : 
			[
				{
					"name" : "HELPSTRING",
					"value" : "Details about finding Threads"
				}
			],
			"type" : "INTERNAL",
			"value" : "[TRUE][v()]"
		},
		{
			"name" : "FIND_PACKAGE_MESSAGE_DETAILS_Vulkan",
			"properties" : 
			[
				{
					"name" : "HELPSTRING",
					"value" : "Details about finding Vulkan"
				}
			],
			"type" : "INTERNAL",
			"value" : "[/usr/local/lib/libvulkan.dylib][/usr/local/include][cfound components: glslc glslangValidator ][v1.3.275()]"
		},
		{
			"name" : "FMT_BINARY_DIR",
			"properties" : 
			[
				{
					"name" : "HELPSTRING",
					"value" : "Value Computed by CMake"
				}
			],
			"type" : "STATIC",
			"value" : "/Users/brk/_private/repos/utils/Camel-Snake-Util/cmake-build-debug-system/vendor/imgui/HBUI/vendor/fmt"
		},
		{
			"name" : "FMT_CMAKE_DIR",
			"properties" : 
			[
				{
					"name" : "HELPSTRING",
					"value" : "Installation directory for cmake files, a relative path that will be joined with /usr/local or an absolute path."
				}
			],
			"type" : "STRING",
			"value" : "lib/cmake/fmt"
		},
		{
			"name" : "FMT_CUDA_TEST",
			"properties" : 
			[
				{
					"name" : "HELPSTRING",
					"value" : "Generate the cuda-test target."
				}
			],
			"type" : "BOOL",
			"value" : "OFF"
		},
		{
			"name" : "FMT_DEBUG_POSTFIX",
			"properties" : 
			[
				{
					"name" : "HELPSTRING",
					"value" : "Debug library postfix."
				}
			],
			"type" : "STRING",
			"value" : "d"
		},
		{
			"name" : "FMT_DOC",
			"properties" : 
			[
				{
					"name" : "HELPSTRING",
					"value" : "Generate the doc target."
				}
			],
			"type" : "BOOL",
			"value" : "OFF"
		},
		{
			"name" : "FMT_FUZZ",
			"properties" : 
			[
				{
					"name" : "HELPSTRING",
					"value" : "Generate the fuzz target."
				}
			],
			"type" : "BOOL",
			"value" : "OFF"
		},
		{
			"name" : "FMT_INC_DIR",
			"properties" : 
			[
				{
					"name" : "HELPSTRING",
					"value" : "Installation directory for include files, a relative path that will be joined with /usr/local or an absolute path."
				}
			],
			"type" : "STRING",
			"value" : "include"
		},
		{
			"name" : "FMT_INSTALL",
			"properties" : 
			[
				{
					"name" : "HELPSTRING",
					"value" : "Generate the install target."
				}
			],
			"type" : "BOOL",
			"value" : "ON"
		},
		{
			"name" : "FMT_IS_TOP_LEVEL",
			"properties" : 
			[
				{
					"name" : "HELPSTRING",
					"value" : "Value Computed by CMake"
				}
			],
			"type" : "STATIC",
			"value" : "OFF"
		},
		{
			"name" : "FMT_LIB_DIR",
			"properties" : 
			[
				{
					"name" : "HELPSTRING",
					"value" : "Installation directory for libraries, a relative path that will be joined to /usr/local or an absolute path."
				}
			],
			"type" : "STRING",
			"value" : "lib"
		},
		{
			"name" : "FMT_MODULE",
			"properties" : 
			[
				{
					"name" : "HELPSTRING",
					"value" : "Build a module instead of a traditional library."
				}
			],
			"type" : "BOOL",
			"value" : "OFF"
		},
		{
			"name" : "FMT_OS",
			"properties" : 
			[
				{
					"name" : "HELPSTRING",
					"value" : "Include core requiring OS (Windows/Posix) "
				}
			],
			"type" : "BOOL",
			"value" : "ON"
		},
		{
			"name" : "FMT_PEDANTIC",
			"properties" : 
			[
				{
					"name" : "HELPSTRING",
					"value" : "Enable extra warnings and expensive tests."
				}
			],
			"type" : "BOOL",
			"value" : "OFF"
		},
		{
			"name" : "FMT_PKGCONFIG_DIR",
			"properties" : 
			[
				{
					"name" : "HELPSTRING",
					"value" : "Installation directory for pkgconfig (.pc) files, a relative path that will be joined with /usr/local or an absolute path."
				}
			],
			"type" : "STRING",
			"value" : "lib/pkgconfig"
		},
		{
			"name" : "FMT_SOURCE_DIR",
			"properties" : 
			[
				{
					"name" : "HELPSTRING",
					"value" : "Value Computed by CMake"
				}
			],
			"type" : "STATIC",
			"value" : "/Users/brk/_private/repos/utils/Camel-Snake-Util/vendor/imgui/HBUI/vendor/fmt"
		},
		{
			"name" : "FMT_SYSTEM_HEADERS",
			"properties" : 
			[
				{
					"name" : "HELPSTRING",
					"value" : "Expose headers with marking them as system."
				}
			],
			"type" : "BOOL",
			"value" : "OFF"
		},
		{
			"name" : "FMT_TEST",
			"properties" : 
			[
				{
					"name" : "HELPSTRING",
					"value" : "Generate the test target."
				}
			],
			"type" : "BOOL",
			"value" : "OFF"
		},
		{
			"name" : "FMT_WERROR",
			"properties" : 
			[
				{
					"name" : "HELPSTRING",
					"value" : "Halt the compilation with an error on compiler warnings."
				}
			],
			"type" : "BOOL",
			"value" : "OFF"
		},
		{
			"name" : "GIT_EXECUTABLE",
			"properties" : 
			[
				{
					"name" : "ADVANCED",
					"value" : "1"
				},
				{
					"name" : "HELPSTRING",
					"value" : "Git command line client"
				}
			],
			"type" : "FILEPATH",
			"value" : "/usr/bin/git"
		},
		{
			"name" : "GLFW_BINARY_DIR",
			"properties" : 
			[
				{
					"name" : "HELPSTRING",
					"value" : "Value Computed by CMake"
				}
			],
			"type" : "STATIC",
			"value" : "/Users/brk/_private/repos/utils/Camel-Snake-Util/cmake-build-debug-system/ImVK/glfw"
		},
		{
			"name" : "GLFW_BUILD_COCOA",
			"properties" : 
			[
				{
					"name" : "HELPSTRING",
					"value" : "Build support for Cocoa"
				}
			],
			"type" : "BOOL",
			"value" : "ON"
		},
		{
			"name" : "GLFW_IS_TOP_LEVEL",
			"properties" : 
			[
				{
					"name" : "HELPSTRING",
					"value" : "Value Computed by CMake"
				}
			],
			"type" : "STATIC",
			"value" : "OFF"
		},
		{
			"name" : "GLFW_LIBRARY_TYPE",
			"properties" : 
			[
				{
					"name" : "HELPSTRING",
					"value" : "Library type override for GLFW (SHARED, STATIC, OBJECT, or empty to follow BUILD_SHARED_LIBS)"
				}
			],
			"type" : "STRING",
			"value" : ""
		},
		{
			"name" : "GLFW_PKG_CONFIG_LIBS_PRIVATE",
			"properties" : 
			[
				{
					"name" : "HELPSTRING",
					"value" : "GLFW pkg-config Libs.private"
				}
			],
			"type" : "INTERNAL",
			"value" : " -framework Cocoa -framework IOKit -framework CoreFoundation"
		},
		{
			"name" : "GLFW_PKG_CONFIG_REQUIRES_PRIVATE",
			"properties" : 
			[
				{
					"name" : "HELPSTRING",
					"value" : "GLFW pkg-config Requires.private"
				}
			],
			"type" : "INTERNAL",
			"value" : ""
		},
		{
			"name" : "GLFW_SOURCE_DIR",
			"properties" : 
			[
				{
					"name" : "HELPSTRING",
					"value" : "Value Computed by CMake"
				}
			],
			"type" : "STATIC",
			"value" : "/Users/brk/_private/repos/utils/Camel-Snake-Util/vendor/glfw"
		},
		{
			"name" : "HAS_NULLPTR_WARNING",
			"properties" : 
			[
				{
					"name" : "HELPSTRING",
					"value" : "Test HAS_NULLPTR_WARNING"
				}
			],
			"type" : "INTERNAL",
			"value" : "1"
		},
		{
			"name" : "HBUI_BINARY_DIR",
			"properties" : 
			[
				{
					"name" : "HELPSTRING",
					"value" : "Value Computed by CMake"
				}
			],
			"type" : "STATIC",
			"value" : "/Users/brk/_private/repos/utils/Camel-Snake-Util/cmake-build-debug-system/vendor/imgui/HBUI"
		},
		{
			"name" : "HBUI_BUILD_EXAMPLE",
			"properties" : 
			[
				{
					"name" : "HELPSTRING",
					"value" : "Build example"
				}
			],
			"type" : "BOOL",
			"value" : "ON"
		},
		{
			"name" : "HBUI_GLFW",
			"properties" : 
			[
				{
					"name" : "HELPSTRING",
					"value" : "HBUI_GLFW"
				}
			],
			"type" : "BOOL",
			"value" : "ON"
		},
		{
			"name" : "HBUI_GLFW_VULKAN",
			"properties" : 
			[
				{
					"name" : "HELPSTRING",
					"value" : "Use VULKAN WITH GLFW"
				}
			],
			"type" : "BOOL",
			"value" : "ON"
		},
		{
			"name" : "HBUI_IS_TOP_LEVEL",
			"properties" : 
			[
				{
					"name" : "HELPSTRING",
					"value" : "Value Computed by CMake"
				}
			],
			"type" : "STATIC",
			"value" : "OFF"
		},
		{
			"name" : "HBUI_SOURCE_DIR",
			"properties" : 
			[
				{
					"name" : "HELPSTRING",
					"value" : "Value Computed by CMake"
				}
			],
			"type" : "STATIC",
			"value" : "/Users/brk/_private/repos/utils/Camel-Snake-Util/vendor/imgui/HBUI"
		},
		{
			"name" : "HBUI_VENDOR_BINARY_DIR",
			"properties" : 
			[
				{
					"name" : "HELPSTRING",
					"value" : "Value Computed by CMake"
				}
			],
			"type" : "STATIC",
			"value" : "/Users/brk/_private/repos/utils/Camel-Snake-Util/cmake-build-debug-system/vendor/imgui/HBUI/vendor"
		},
		{
			"name" : "HBUI_VENDOR_IS_TOP_LEVEL",
			"properties" : 
			[
				{
					"name" : "HELPSTRING",
					"value" : "Value Computed by CMake"
				}
			],
			"type" : "STATIC",
			"value" : "OFF"
		},
		{
			"name" : "HBUI_VENDOR_SOURCE_DIR",
			"properties" : 
			[
				{
					"name" : "HELPSTRING",
					"value" : "Value Computed by CMake"
				}
			],
			"type" : "STATIC",
			"value" : "/Users/brk/_private/repos/utils/Camel-Snake-Util/vendor/imgui/HBUI/vendor"
		},
		{
			"name" : "HBUI_WITH_DEBUG_WINDOW",
			"properties" : 
			[
				{
					"name" : "HELPSTRING",
					"value" : "HBUI_WITH_DEBUG_WINDOW"
				}
			],
			"type" : "BOOL",
			"value" : "OFF"
		},
		{
			"name" : "HTLATEX_COMPILER",
			"properties" : 
			[
				{
					"name" : "ADVANCED",
					"value" : "1"
				},
				{
					"name" : "HELPSTRING",
					"value" : "Path to a program."
				}
			],
			"type" : "FILEPATH",
			"value" : "HTLATEX_COMPILER-NOTFOUND"
		},
		{
			"name" : "IMVK_DOWNLOAD_GLFW",
			"properties" : 
			[
				{
					"name" : "HELPSTRING",
					"value" : "Download GLFW"
				}
			],
			"type" : "BOOL",
			"value" : "ON"
		},
		{
			"name" : "ImVk-example_BINARY_DIR",
			"properties" : 
			[
				{
					"name" : "HELPSTRING",
					"value" : "Value Computed by CMake"
				}
			],
			"type" : "STATIC",
			"value" : "/Users/brk/_private/repos/utils/Camel-Snake-Util/cmake-build-debug-system/example"
		},
		{
			"name" : "ImVk-example_IS_TOP_LEVEL",
			"properties" : 
			[
				{
					"name" : "HELPSTRING",
					"value" : "Value Computed by CMake"
				}
			],
			"type" : "STATIC",
			"value" : "OFF"
		},
		{
			"name" : "ImVk-example_SOURCE_DIR",
			"properties" : 
			[
				{
					"name" : "HELPSTRING",
					"value" : "Value Computed by CMake"
				}
			],
			"type" : "STATIC",
			"value" : "/Users/brk/_private/repos/utils/Camel-Snake-Util/vendor/imgui/example"
		},
		{
			"name" : "ImVk_BINARY_DIR",
			"properties" : 
			[
				{
					"name" : "HELPSTRING",
					"value" : "Value Computed by CMake"
				}
			],
			"type" : "STATIC",
			"value" : "/Users/brk/_private/repos/utils/Camel-Snake-Util/cmake-build-debug-system/ImVK"
		},
		{
			"name" : "ImVk_IS_TOP_LEVEL",
			"properties" : 
			[
				{
					"name" : "HELPSTRING",
					"value" : "Value Computed by CMake"
				}
			],
			"type" : "STATIC",
			"value" : "OFF"
		},
		{
			"name" : "ImVk_SOURCE_DIR",
			"properties" : 
			[
				{
					"name" : "HELPSTRING",
					"value" : "Value Computed by CMake"
				}
			],
			"type" : "STATIC",
			"value" : "/Users/brk/_private/repos/utils/Camel-Snake-Util/vendor/imgui/ImVK"
		},
		{
			"name" : "LATEX2HTML_CONVERTER",
			"properties" : 
			[
				{
					"name" : "ADVANCED",
					"value" : "1"
				},
				{
					"name" : "HELPSTRING",
					"value" : "Path to a program."
				}
			],
			"type" : "FILEPATH",
			"value" : "LATEX2HTML_CONVERTER-NOTFOUND"
		},
		{
			"name" : "LATEX_COMPILER",
			"properties" : 
			[
				{
					"name" : "ADVANCED",
					"value" : "1"
				},
				{
					"name" : "HELPSTRING",
					"value" : "Path to a program."
				}
			],
			"type" : "FILEPATH",
			"value" : "LATEX_COMPILER-NOTFOUND"
		},
		{
			"name" : "LOCAL_AUTHENTICATION_LIBRARY",
			"properties" : 
			[
				{
					"name" : "HELPSTRING",
					"value" : "Path to a library."
				}
			],
			"type" : "FILEPATH",
			"value" : "/Applications/Xcode.app/Contents/Developer/Platforms/MacOSX.platform/Developer/SDKs/MacOSX14.4.sdk/System/Library/Frameworks/LocalAuthentication.framework"
		},
		{
			"name" : "LUALATEX_COMPILER",
			"properties" : 
			[
				{
					"name" : "ADVANCED",
					"value" : "1"
				},
				{
					"name" : "HELPSTRING",
					"value" : "Path to a program."
				}
			],
			"type" : "FILEPATH",
			"value" : "LUALATEX_COMPILER-NOTFOUND"
		},
		{
			"name" : "MAGIC_ENUM_OPT_BUILD_EXAMPLES",
			"properties" : 
			[
				{
					"name" : "HELPSTRING",
					"value" : "Build magic_enum examples"
				}
			],
			"type" : "BOOL",
			"value" : "OFF"
		},
		{
			"name" : "MAGIC_ENUM_OPT_BUILD_TESTS",
			"properties" : 
			[
				{
					"name" : "HELPSTRING",
					"value" : "Build and perform magic_enum tests"
				}
			],
			"type" : "BOOL",
			"value" : "OFF"
		},
		{
			"name" : "MAGIC_ENUM_OPT_INSTALL",
			"properties" : 
			[
				{
					"name" : "HELPSTRING",
					"value" : "Generate and install magic_enum target"
				}
			],
			"type" : "BOOL",
			"value" : "OFF"
		},
		{
			"name" : "MAKEINDEX_COMPILER",
			"properties" : 
			[
				{
					"name" : "ADVANCED",
					"value" : "1"
				},
				{
					"name" : "HELPSTRING",
					"value" : "Path to a program."
				}
			],
			"type" : "FILEPATH",
			"value" : "MAKEINDEX_COMPILER-NOTFOUND"
		},
		{
			"name" : "PDFLATEX_COMPILER",
			"properties" : 
			[
				{
					"name" : "ADVANCED",
					"value" : "1"
				},
				{
					"name" : "HELPSTRING",
					"value" : "Path to a program."
				}
			],
			"type" : "FILEPATH",
			"value" : "PDFLATEX_COMPILER-NOTFOUND"
		},
		{
			"name" : "PDFTOPS_CONVERTER",
			"properties" : 
			[
				{
					"name" : "ADVANCED",
					"value" : "1"
				},
				{
					"name" : "HELPSTRING",
					"value" : "Path to a program."
				}
			],
			"type" : "FILEPATH",
			"value" : "PDFTOPS_CONVERTER-NOTFOUND"
		},
		{
			"name" : "PS2PDF_CONVERTER",
			"properties" : 
			[
				{
					"name" : "ADVANCED",
					"value" : "1"
				},
				{
					"name" : "HELPSTRING",
					"value" : "Path to a program."
				}
			],
			"type" : "FILEPATH",
			"value" : "PS2PDF_CONVERTER-NOTFOUND"
		},
		{
			"name" : "Python3_EXECUTABLE",
			"properties" : 
			[
				{
					"name" : "ADVANCED",
					"value" : "1"
				},
				{
					"name" : "HELPSTRING",
					"value" : "Path to a program."
				}
			],
			"type" : "FILEPATH",
			"value" : "/opt/homebrew/bin/python3"
		},
		{
			"name" : "SECURITY_LIBRARY",
			"properties" : 
			[
				{
					"name" : "HELPSTRING",
					"value" : "Path to a library."
				}
			],
			"type" : "FILEPATH",
			"value" : "/Applications/Xcode.app/Contents/Developer/Platforms/MacOSX.platform/Developer/SDKs/MacOSX14.4.sdk/System/Library/Frameworks/Security.framework"
		},
		{
			"name" : "SPDLOG_BUILD_ALL",
			"properties" : 
			[
				{
					"name" : "HELPSTRING",
					"value" : "Build all artifacts"
				}
			],
			"type" : "BOOL",
			"value" : "OFF"
		},
		{
			"name" : "SPDLOG_BUILD_BENCH",
			"properties" : 
			[
				{
					"name" : "HELPSTRING",
					"value" : "Build benchmarks (Requires https://github.com/google/benchmark.git to be installed)"
				}
			],
			"type" : "BOOL",
			"value" : "OFF"
		},
		{
			"name" : "SPDLOG_BUILD_EXAMPLE",
			"properties" : 
			[
				{
					"name" : "HELPSTRING",
					"value" : "Build example"
				}
			],
			"type" : "BOOL",
			"value" : "OFF"
		},
		{
			"name" : "SPDLOG_BUILD_EXAMPLE_HO",
			"properties" : 
			[
				{
					"name" : "HELPSTRING",
					"value" : "Build header only example"
				}
			],
			"type" : "BOOL",
			"value" : "OFF"
		},
		{
			"name" : "SPDLOG_BUILD_PIC",
			"properties" : 
			[
				{
					"name" : "HELPSTRING",
					"value" : "Build position independent code (-fPIC)"
				}
			],
			"type" : "BOOL",
			"value" : "OFF"
		},
		{
			"name" : "SPDLOG_BUILD_SHARED",
			"properties" : 
			[
				{
					"name" : "HELPSTRING",
					"value" : "Build shared library"
				}
			],
			"type" : "BOOL",
			"value" : "OFF"
		},
		{
			"name" : "SPDLOG_BUILD_TESTS",
			"properties" : 
			[
				{
					"name" : "HELPSTRING",
					"value" : "Build tests"
				}
			],
			"type" : "BOOL",
			"value" : "OFF"
		},
		{
			"name" : "SPDLOG_BUILD_TESTS_HO",
			"properties" : 
			[
				{
					"name" : "HELPSTRING",
					"value" : "Build tests using the header only version"
				}
			],
			"type" : "BOOL",
			"value" : "OFF"
		},
		{
			"name" : "SPDLOG_BUILD_WARNINGS",
			"properties" : 
			[
				{
					"name" : "HELPSTRING",
					"value" : "Enable compiler warnings"
				}
			],
			"type" : "BOOL",
			"value" : "OFF"
		},
		{
			"name" : "SPDLOG_CLOCK_COARSE",
			"properties" : 
			[
				{
					"name" : "HELPSTRING",
					"value" : "non supported option"
				}
			],
			"type" : "BOOL",
			"value" : "OFF"
		},
		{
			"name" : "SPDLOG_DISABLE_DEFAULT_LOGGER",
			"properties" : 
			[
				{
					"name" : "HELPSTRING",
					"value" : "Disable default logger creation"
				}
			],
			"type" : "BOOL",
			"value" : "OFF"
		},
		{
			"name" : "SPDLOG_ENABLE_PCH",
			"properties" : 
			[
				{
					"name" : "HELPSTRING",
					"value" : "Build static or shared library using precompiled header to speed up compilation time"
				}
			],
			"type" : "BOOL",
			"value" : "OFF"
		},
		{
			"name" : "SPDLOG_FMT_EXTERNAL",
			"properties" : 
			[
				{
					"name" : "HELPSTRING",
					"value" : "Use external fmt library instead of bundled"
				}
			],
			"type" : "BOOL",
			"value" : "ON"
		},
		{
			"name" : "SPDLOG_FMT_EXTERNAL_HO",
			"properties" : 
			[
				{
					"name" : "HELPSTRING",
					"value" : "Use external fmt header-only library instead of bundled"
				}
			],
			"type" : "BOOL",
			"value" : "OFF"
		},
		{
			"name" : "SPDLOG_INSTALL",
			"properties" : 
			[
				{
					"name" : "HELPSTRING",
					"value" : "Generate the install target"
				}
			],
			"type" : "BOOL",
			"value" : "OFF"
		},
		{
			"name" : "SPDLOG_NO_ATOMIC_LEVELS",
			"properties" : 
			[
				{
					"name" : "HELPSTRING",
					"value" : "prevent spdlog from using of std::atomic log levels (use only if your code never modifies log levels concurrently"
				}
			],
			"type" : "BOOL",
			"value" : "OFF"
		},
		{
			"name" : "SPDLOG_NO_EXCEPTIONS",
			"properties" : 
			[
				{
					"name" : "HELPSTRING",
					"value" : "Compile with -fno-exceptions. Call abort() on any spdlog exceptions"
				}
			],
			"type" : "BOOL",
			"value" : "OFF"
		},
		{
			"name" : "SPDLOG_NO_THREAD_ID",
			"properties" : 
			[
				{
					"name" : "HELPSTRING",
					"value" : "prevent spdlog from querying the thread id on each log call if thread id is not needed"
				}
			],
			"type" : "BOOL",
			"value" : "OFF"
		},
		{
			"name" : "SPDLOG_NO_TLS",
			"properties" : 
			[
				{
					"name" : "HELPSTRING",
					"value" : "prevent spdlog from using thread local storage"
				}
			],
			"type" : "BOOL",
			"value" : "OFF"
		},
		{
			"name" : "SPDLOG_PREVENT_CHILD_FD",
			"properties" : 
			[
				{
					"name" : "HELPSTRING",
					"value" : "Prevent from child processes to inherit log file descriptors"
				}
			],
			"type" : "BOOL",
			"value" : "OFF"
		},
		{
			"name" : "SPDLOG_SANITIZE_ADDRESS",
			"properties" : 
			[
				{
					"name" : "HELPSTRING",
					"value" : "Enable address sanitizer in tests"
				}
			],
			"type" : "BOOL",
			"value" : "OFF"
		},
		{
			"name" : "SPDLOG_SYSTEM_INCLUDES",
			"properties" : 
			[
				{
					"name" : "HELPSTRING",
					"value" : "Include as system headers (skip for clang-tidy)."
				}
			],
			"type" : "BOOL",
			"value" : "OFF"
		},
		{
			"name" : "SPDLOG_TIDY",
			"properties" : 
			[
				{
					"name" : "HELPSTRING",
					"value" : "run clang-tidy"
				}
			],
			"type" : "BOOL",
			"value" : "OFF"
		},
		{
			"name" : "SPDLOG_USE_STD_FORMAT",
			"properties" : 
			[
				{
					"name" : "HELPSTRING",
					"value" : "Use std::format instead of fmt library."
				}
			],
			"type" : "BOOL",
			"value" : "OFF"
		},
		{
			"name" : "SPDLOG_WCHAR_FILENAMES",
			"properties" : 
			[
				{
					"name" : "HELPSTRING",
					"value" : "non supported option"
				}
			],
			"type" : "BOOL",
			"value" : "OFF"
		},
		{
			"name" : "SPDLOG_WCHAR_SUPPORT",
			"properties" : 
			[
				{
					"name" : "HELPSTRING",
					"value" : "non supported option"
				}
			],
			"type" : "BOOL",
			"value" : "OFF"
		},
		{
			"name" : "SPHINX_EXECUTABLE",
			"properties" : 
			[
				{
					"name" : "ADVANCED",
					"value" : "1"
				},
				{
					"name" : "HELPSTRING",
					"value" : "Sphinx documentation generator"
				}
			],
			"type" : "FILEPATH",
			"value" : "SPHINX_EXECUTABLE-NOTFOUND"
		},
		{
			"name" : "UAPP_BUILD_DOCUMENTATION",
			"properties" : 
			[
				{
					"name" : "HELPSTRING",
					"value" : "Build documentation"
				}
			],
			"type" : "BOOL",
			"value" : "OFF"
		},
		{
			"name" : "UAPP_BUILD_EXAMPLES",
			"properties" : 
			[
				{
					"name" : "HELPSTRING",
					"value" : "Build examples"
				}
			],
			"type" : "BOOL",
			"value" : "OFF"
		},
		{
			"name" : "UAPP_BUILD_TESTS",
			"properties" : 
			[
				{
					"name" : "HELPSTRING",
					"value" : "Build unit tests"
				}
			],
			"type" : "BOOL",
			"value" : "OFF"
		},
		{
			"name" : "UAPP_ENABLE_CLANG_TIDY",
			"properties" : 
			[
				{
					"name" : "HELPSTRING",
					"value" : "Enable static analysis with clang-tidy"
				}
			],
			"type" : "BOOL",
			"value" : "OFF"
		},
		{
			"name" : "UAPP_ENABLE_COVERAGE",
			"properties" : 
			[
				{
					"name" : "HELPSTRING",
					"value" : "Enable coverage reporting for gcc/clang"
				}
			],
			"type" : "BOOL",
			"value" : "OFF"
		},
		{
			"name" : "UAPP_ENABLE_INCLUDE_WHAT_YOU_USE",
			"properties" : 
			[
				{
					"name" : "HELPSTRING",
					"value" : "Enable static analysis with include-what-you-use"
				}
			],
			"type" : "BOOL",
			"value" : "OFF"
		},
		{
			"name" : "UAPP_ENABLE_SANITIZER_ADDRESS",
			"properties" : 
			[
				{
					"name" : "HELPSTRING",
					"value" : "Enable address sanitizer"
				}
			],
			"type" : "BOOL",
			"value" : "OFF"
		},
		{
			"name" : "UAPP_ENABLE_SANITIZER_LEAK",
			"properties" : 
			[
				{
					"name" : "HELPSTRING",
					"value" : "Enable leak sanitizer"
				}
			],
			"type" : "BOOL",
			"value" : "OFF"
		},
		{
			"name" : "UAPP_ENABLE_SANITIZER_MEMORY",
			"properties" : 
			[
				{
					"name" : "HELPSTRING",
					"value" : "Enable memory sanitizer"
				}
			],
			"type" : "BOOL",
			"value" : "OFF"
		},
		{
			"name" : "UAPP_ENABLE_SANITIZER_THREAD",
			"properties" : 
			[
				{
					"name" : "HELPSTRING",
					"value" : "Enable thread sanitizer"
				}
			],
			"type" : "BOOL",
			"value" : "OFF"
		},
		{
			"name" : "UAPP_ENABLE_SANITIZER_UNDEFINED_BEHAVIOR",
			"properties" : 
			[
				{
					"name" : "HELPSTRING",
					"value" : "Enable undefined behavior sanitizer"
				}
			],
			"type" : "BOOL",
			"value" : "OFF"
		},
		{
			"name" : "UAPP_INTERNAL_OPEN62541",
			"properties" : 
			[
				{
					"name" : "HELPSTRING",
					"value" : "Use internal open62541 library"
				}
			],
			"type" : "BOOL",
			"value" : "ON"
		},
		{
			"name" : "UAPP_WARNINGS_AS_ERRORS",
			"properties" : 
			[
				{
					"name" : "HELPSTRING",
					"value" : "Treat warnings as errors"
				}
			],
			"type" : "BOOL",
			"value" : "OFF"
		},
		{
			"name" : "UA_AMALGAMATION_ARCHITECTURES",
			"properties" : 
			[
				{
					"name" : "ADVANCED",
					"value" : "1"
				},
				{
					"name" : "HELPSTRING",
					"value" : "List of architectures to include in amalgamation"
				}
			],
			"type" : "STRING",
			"value" : ""
		},
		{
			"name" : "UA_ARCHITECTURE",
			"properties" : 
			[
				{
					"name" : "HELPSTRING",
					"value" : ""
				},
				{
					"name" : "STRINGS",
					"value" : "None;eCos;freertosLWIP;posix;vxworks;wec7;win32"
				}
			],
			"type" : "STRING",
			"value" : "posix"
		},
		{
			"name" : "UA_ARCH_ADD_FLAGS",
			"properties" : 
			[
				{
					"name" : "ADVANCED",
					"value" : "1"
				},
				{
					"name" : "HELPSTRING",
					"value" : "Flags to be added to compilation that depends on the architecure"
				}
			],
			"type" : "STRING",
			"value" : ""
		},
		{
			"name" : "UA_ARCH_EXTRA_INCLUDES",
			"properties" : 
			[
				{
					"name" : "ADVANCED",
					"value" : "1"
				},
				{
					"name" : "HELPSTRING",
					"value" : "Folders to include from the architecture"
				}
			],
			"type" : "STRING",
			"value" : ""
		},
		{
			"name" : "UA_ARCH_LINKER_FLAGS",
			"properties" : 
			[
				{
					"name" : "ADVANCED",
					"value" : "1"
				},
				{
					"name" : "HELPSTRING",
					"value" : "Linker Flags to be added to compilation that depends on the architecure"
				}
			],
			"type" : "STRING",
			"value" : ""
		},
		{
			"name" : "UA_ARCH_REMOVE_FLAGS",
			"properties" : 
			[
				{
					"name" : "ADVANCED",
					"value" : "1"
				},
				{
					"name" : "HELPSTRING",
					"value" : "Flags to be removed from compilation that depends on the architecure"
				}
			],
			"type" : "STRING",
			"value" : ""
		},
		{
			"name" : "UA_BUILD_EXAMPLES",
			"properties" : 
			[
				{
					"name" : "HELPSTRING",
					"value" : "Build example servers and clients"
				}
			],
			"type" : "BOOL",
			"value" : "OFF"
		},
		{
			"name" : "UA_BUILD_FUZZING",
			"properties" : 
			[
				{
					"name" : "ADVANCED",
					"value" : "1"
				},
				{
					"name" : "HELPSTRING",
					"value" : "Build the fuzzing executables"
				}
			],
			"type" : "BOOL",
			"value" : "OFF"
		},
		{
			"name" : "UA_BUILD_FUZZING_CORPUS",
			"properties" : 
			[
				{
					"name" : "ADVANCED",
					"value" : "1"
				},
				{
					"name" : "HELPSTRING",
					"value" : "Build the fuzzing corpus"
				}
			],
			"type" : "BOOL",
			"value" : "OFF"
		},
		{
			"name" : "UA_BUILD_OSS_FUZZ",
			"properties" : 
			[
				{
					"name" : "ADVANCED",
					"value" : "1"
				},
				{
					"name" : "HELPSTRING",
					"value" : "Special build switch used in oss-fuzz"
				}
			],
			"type" : "BOOL",
			"value" : "OFF"
		},
		{
			"name" : "UA_BUILD_TOOLS",
			"properties" : 
			[
				{
					"name" : "HELPSTRING",
					"value" : "Build OPC UA shell tools"
				}
			],
			"type" : "BOOL",
			"value" : "OFF"
		},
		{
			"name" : "UA_BUILD_UNIT_TESTS",
			"properties" : 
			[
				{
					"name" : "HELPSTRING",
					"value" : "Build the unit tests"
				}
			],
			"type" : "BOOL",
			"value" : "OFF"
		},
		{
			"name" : "UA_DEBUG",
			"properties" : 
			[
				{
					"name" : "ADVANCED",
					"value" : "1"
				},
				{
					"name" : "HELPSTRING",
					"value" : "Enable assertions and additional functionality that should not be included in release builds"
				}
			],
			"type" : "BOOL",
			"value" : "OFF"
		},
		{
			"name" : "UA_DEBUG_DUMP_PKGS",
			"properties" : 
			[
				{
					"name" : "ADVANCED",
					"value" : "1"
				},
				{
					"name" : "HELPSTRING",
					"value" : "Dump every package received by the server as hexdump format"
				}
			],
			"type" : "BOOL",
			"value" : "OFF"
		},
		{
			"name" : "UA_DEBUG_FILE_LINE_INFO",
			"properties" : 
			[
				{
					"name" : "ADVANCED",
					"value" : "1"
				},
				{
					"name" : "HELPSTRING",
					"value" : "Enable file and line information as additional debugging output for error messages"
				}
			],
			"type" : "BOOL",
			"value" : "OFF"
		},
		{
			"name" : "UA_ENABLE_AMALGAMATION",
			"properties" : 
			[
				{
					"name" : "HELPSTRING",
					"value" : "Concatenate the library to a single file open62541.h/.c"
				}
			],
			"type" : "BOOL",
			"value" : "OFF"
		},
		{
			"name" : "UA_ENABLE_CLANG_COV",
			"properties" : 
			[
				{
					"name" : "ADVANCED",
					"value" : "1"
				},
				{
					"name" : "HELPSTRING",
					"value" : "Enable clang coverage"
				}
			],
			"type" : "BOOL",
			"value" : "OFF"
		},
		{
			"name" : "UA_ENABLE_COVERAGE",
			"properties" : 
			[
				{
					"name" : "ADVANCED",
					"value" : "1"
				},
				{
					"name" : "HELPSTRING",
					"value" : "Enable gcov coverage"
				}
			],
			"type" : "BOOL",
			"value" : "OFF"
		},
		{
			"name" : "UA_ENABLE_DA",
			"properties" : 
			[
				{
					"name" : "HELPSTRING",
					"value" : "Enable OPC UA DataAccess (Part 8) definitions"
				}
			],
			"type" : "BOOL",
			"value" : "ON"
		},
		{
			"name" : "UA_ENABLE_DEBUG_SANITIZER",
			"properties" : 
			[
				{
					"name" : "ADVANCED",
					"value" : "1"
				},
				{
					"name" : "HELPSTRING",
					"value" : ""
				}
			],
			"type" : "BOOL",
			"value" : "OFF"
		},
		{
			"name" : "UA_ENABLE_DETERMINISTIC_RNG",
			"properties" : 
			[
				{
					"name" : "ADVANCED",
					"value" : "1"
				},
				{
					"name" : "HELPSTRING",
					"value" : "Do not seed the random number generator (e.g. for unit tests)."
				}
			],
			"type" : "BOOL",
			"value" : "OFF"
		},
		{
			"name" : "UA_ENABLE_DIAGNOSTICS",
			"properties" : 
			[
				{
					"name" : "HELPSTRING",
					"value" : "Enable diagnostics information exposed by the server"
				}
			],
			"type" : "BOOL",
			"value" : "OFF"
		},
		{
			"name" : "UA_ENABLE_DISCOVERY",
			"properties" : 
			[
				{
					"name" : "HELPSTRING",
					"value" : "Enable Discovery Service (LDS)"
				}
			],
			"type" : "BOOL",
			"value" : "OFF"
		},
		{
			"name" : "UA_ENABLE_DISCOVERY_MULTICAST",
			"properties" : 
			[
				{
					"name" : "ADVANCED",
					"value" : "1"
				},
				{
					"name" : "HELPSTRING",
					"value" : "Enable Discovery Service with multicast support (LDS-ME)"
				}
			],
			"type" : "BOOL",
			"value" : "OFF"
		},
		{
			"name" : "UA_ENABLE_DISCOVERY_SEMAPHORE",
			"properties" : 
			[
				{
					"name" : "ADVANCED",
					"value" : "1"
				},
				{
					"name" : "HELPSTRING",
					"value" : "Enable Discovery Semaphore support"
				}
			],
			"type" : "BOOL",
			"value" : "ON"
		},
		{
			"name" : "UA_ENABLE_ENCRYPTION",
			"properties" : 
			[
				{
					"name" : "HELPSTRING",
					"value" : "Encryption support (Libressl EXPERIMENTAL)"
				},
				{
					"name" : "STRINGS",
					"value" : "OFF;MBEDTLS;OPENSSL;LIBRESSL"
				}
			],
			"type" : "STRING",
			"value" : "OFF"
		},
		{
			"name" : "UA_ENABLE_ENCRYPTION_MBEDTLS",
			"properties" : 
			[
				{
					"name" : "ADVANCED",
					"value" : "1"
				},
				{
					"name" : "HELPSTRING",
					"value" : "Deprecated: Enable encryption support (uses mbedTLS)"
				}
			],
			"type" : "BOOL",
			"value" : "OFF"
		},
		{
			"name" : "UA_ENABLE_ENCRYPTION_OPENSSL",
			"properties" : 
			[
				{
					"name" : "ADVANCED",
					"value" : "1"
				},
				{
					"name" : "HELPSTRING",
					"value" : "Deprecated: Enable encryption support (uses openssl)"
				}
			],
			"type" : "BOOL",
			"value" : "OFF"
		},
		{
			"name" : "UA_ENABLE_ENCRYPTION_TPM2",
			"properties" : 
			[
				{
					"name" : "HELPSTRING",
					"value" : "TPM encryption support"
				},
				{
					"name" : "STRINGS",
					"value" : "ON;OFF"
				}
			],
			"type" : "STRING",
			"value" : "OFF"
		},
		{
			"name" : "UA_ENABLE_EXPERIMENTAL_HISTORIZING",
			"properties" : 
			[
				{
					"name" : "ADVANCED",
					"value" : "1"
				},
				{
					"name" : "HELPSTRING",
					"value" : "Enable support for experimental historical access features (client)"
				}
			],
			"type" : "BOOL",
			"value" : "OFF"
		},
		{
			"name" : "UA_ENABLE_HARDENING",
			"properties" : 
			[
				{
					"name" : "ADVANCED",
					"value" : "1"
				},
				{
					"name" : "HELPSTRING",
					"value" : "Enable Hardening measures (e.g. Stack-Protectors and Fortify)"
				}
			],
			"type" : "BOOL",
			"value" : "ON"
		},
		{
			"name" : "UA_ENABLE_HISTORIZING",
			"properties" : 
			[
				{
					"name" : "HELPSTRING",
					"value" : "Enable basic support for historical access (client and server)"
				}
			],
			"type" : "BOOL",
			"value" : "OFF"
		},
		{
			"name" : "UA_ENABLE_IMMUTABLE_NODES",
			"properties" : 
			[
				{
					"name" : "ADVANCED",
					"value" : "1"
				},
				{
					"name" : "HELPSTRING",
					"value" : "Nodes in the information model are not edited but copied and replaced"
				}
			],
			"type" : "BOOL",
			"value" : "OFF"
		},
		{
			"name" : "UA_ENABLE_JSON_ENCODING",
			"properties" : 
			[
				{
					"name" : "HELPSTRING",
					"value" : "Enable JSON encoding"
				}
			],
			"type" : "BOOL",
			"value" : "OFF"
		},
		{
			"name" : "UA_ENABLE_MALLOC_SINGLETON",
			"properties" : 
			[
				{
					"name" : "ADVANCED",
					"value" : "1"
				},
				{
					"name" : "HELPSTRING",
					"value" : "Use a global variable pointer for malloc (and free, ...) that can be switched at runtime"
				}
			],
			"type" : "BOOL",
			"value" : "OFF"
		},
		{
			"name" : "UA_ENABLE_METHODCALLS",
			"properties" : 
			[
				{
					"name" : "HELPSTRING",
					"value" : "Enable the Method service set"
				}
			],
			"type" : "BOOL",
			"value" : "ON"
		},
		{
			"name" : "UA_ENABLE_MQTT_TLS",
			"properties" : 
			[
				{
					"name" : "ADVANCED",
					"value" : "1"
				},
				{
					"name" : "HELPSTRING",
					"value" : "Enable TLS support for publish/subscribe with mqtt"
				}
			],
			"type" : "BOOL",
			"value" : "OFF"
		},
		{
			"name" : "UA_ENABLE_MQTT_TLS_MBEDTLS",
			"properties" : 
			[
				{
					"name" : "ADVANCED",
					"value" : "1"
				},
				{
					"name" : "HELPSTRING",
					"value" : "Enable TLS support for publish/subscribe with mqtt (use MBEDTLS)"
				}
			],
			"type" : "BOOL",
			"value" : "OFF"
		},
		{
			"name" : "UA_ENABLE_MQTT_TLS_OPENSSL",
			"properties" : 
			[
				{
					"name" : "ADVANCED",
					"value" : "1"
				},
				{
					"name" : "HELPSTRING",
					"value" : "Enable TLS support for publish/subscribe with mqtt (use OpenSSL)"
				}
			],
			"type" : "BOOL",
			"value" : "OFF"
		},
		{
			"name" : "UA_ENABLE_NODEMANAGEMENT",
			"properties" : 
			[
				{
					"name" : "ADVANCED",
					"value" : "1"
				},
				{
					"name" : "HELPSTRING",
					"value" : "Enable dynamic addition and removal of nodes at runtime"
				}
			],
			"type" : "BOOL",
			"value" : "ON"
		},
		{
			"name" : "UA_ENABLE_NODESET_COMPILER_DESCRIPTIONS",
			"properties" : 
			[
				{
					"name" : "ADVANCED",
					"value" : "1"
				},
				{
					"name" : "HELPSTRING",
					"value" : "Set node description attribute for nodeset compiler generated nodes"
				}
			],
			"type" : "BOOL",
			"value" : "ON"
		},
		{
			"name" : "UA_ENABLE_PARSING",
			"properties" : 
			[
				{
					"name" : "ADVANCED",
					"value" : "1"
				},
				{
					"name" : "HELPSTRING",
					"value" : "Utility functions that require parsing (e.g. NodeId expressions)"
				}
			],
			"type" : "BOOL",
			"value" : "ON"
		},
		{
			"name" : "UA_ENABLE_PUBSUB",
			"properties" : 
			[
				{
					"name" : "HELPSTRING",
					"value" : "Enable the PubSub protocol"
				}
			],
			"type" : "BOOL",
			"value" : "OFF"
		},
		{
			"name" : "UA_ENABLE_PUBSUB_BUFMALLOC",
			"properties" : 
			[
				{
					"name" : "ADVANCED",
					"value" : "1"
				},
				{
					"name" : "HELPSTRING",
					"value" : "Enable allocation with static memory buffer for time critical PubSub parts"
				}
			],
			"type" : "BOOL",
			"value" : "OFF"
		},
		{
			"name" : "UA_ENABLE_PUBSUB_DELTAFRAMES",
			"properties" : 
			[
				{
					"name" : "HELPSTRING",
					"value" : "Enable sending of delta frames with only the changes"
				}
			],
			"type" : "BOOL",
			"value" : "OFF"
		},
		{
			"name" : "UA_ENABLE_PUBSUB_ENCRYPTION",
			"properties" : 
			[
				{
					"name" : "ADVANCED",
					"value" : "1"
				},
				{
					"name" : "HELPSTRING",
					"value" : "Enable encryption of the PubSub payload"
				}
			],
			"type" : "BOOL",
			"value" : "OFF"
		},
		{
			"name" : "UA_ENABLE_PUBSUB_ETH_UADP",
			"properties" : 
			[
				{
					"name" : "HELPSTRING",
					"value" : "Enable publish/subscribe UADP over Ethernet"
				}
			],
			"type" : "BOOL",
			"value" : "OFF"
		},
		{
			"name" : "UA_ENABLE_PUBSUB_FILE_CONFIG",
			"properties" : 
			[
				{
					"name" : "ADVANCED",
					"value" : "1"
				},
				{
					"name" : "HELPSTRING",
					"value" : "Enable loading PubSub Config from file extension"
				}
			],
			"type" : "BOOL",
			"value" : "OFF"
		},
		{
			"name" : "UA_ENABLE_PUBSUB_INFORMATIONMODEL",
			"properties" : 
			[
				{
					"name" : "HELPSTRING",
					"value" : "Enable PubSub information model twin"
				}
			],
			"type" : "BOOL",
			"value" : "OFF"
		},
		{
			"name" : "UA_ENABLE_PUBSUB_INFORMATIONMODEL_METHODS",
			"properties" : 
			[
				{
					"name" : "HELPSTRING",
					"value" : "Enable PubSub informationmodel methods"
				}
			],
			"type" : "BOOL",
			"value" : "OFF"
		},
		{
			"name" : "UA_ENABLE_PUBSUB_MONITORING",
			"properties" : 
			[
				{
					"name" : "ADVANCED",
					"value" : "1"
				},
				{
					"name" : "HELPSTRING",
					"value" : "Enable monitoring of PubSub components (e.g. MessageReceiveTimeout)"
				}
			],
			"type" : "BOOL",
			"value" : "OFF"
		},
		{
			"name" : "UA_ENABLE_PUBSUB_MQTT",
			"properties" : 
			[
				{
					"name" : "ADVANCED",
					"value" : "1"
				},
				{
					"name" : "HELPSTRING",
					"value" : "Enable publish/subscribe with mqtt (experimental)"
				}
			],
			"type" : "BOOL",
			"value" : "OFF"
		},
		{
			"name" : "UA_ENABLE_QUERY",
			"properties" : 
			[
				{
					"name" : "ADVANCED",
					"value" : "1"
				},
				{
					"name" : "HELPSTRING",
					"value" : "Enable query support in the client (most servers don't support it)"
				}
			],
			"type" : "BOOL",
			"value" : "OFF"
		},
		{
			"name" : "UA_ENABLE_STATIC_ANALYZER",
			"properties" : 
			[
				{
					"name" : "ADVANCED",
					"value" : "1"
				},
				{
					"name" : "HELPSTRING",
					"value" : "Enable installed static analyzer during build process (off/minimal/reduced/full)"
				},
				{
					"name" : "STRINGS",
					"value" : "OFF;MINIMAL;REDUCED;FULL"
				}
			],
			"type" : "STRING",
			"value" : "OFF"
		},
		{
			"name" : "UA_ENABLE_STATUSCODE_DESCRIPTIONS",
			"properties" : 
			[
				{
					"name" : "ADVANCED",
					"value" : "1"
				},
				{
					"name" : "HELPSTRING",
					"value" : "Enable conversion of StatusCode to human-readable error message"
				}
			],
			"type" : "BOOL",
			"value" : "ON"
		},
		{
			"name" : "UA_ENABLE_SUBSCRIPTIONS",
			"properties" : 
			[
				{
					"name" : "HELPSTRING",
					"value" : "Enable subscriptions support"
				}
			],
			"type" : "BOOL",
			"value" : "ON"
		},
		{
			"name" : "UA_ENABLE_SUBSCRIPTIONS_ALARMS_CONDITIONS",
			"properties" : 
			[
				{
					"name" : "ADVANCED",
					"value" : "1"
				},
				{
					"name" : "HELPSTRING",
					"value" : "Enable the use of A&C. (EXPERIMENTAL)"
				}
			],
			"type" : "BOOL",
			"value" : "OFF"
		},
		{
			"name" : "UA_ENABLE_SUBSCRIPTIONS_EVENTS",
			"properties" : 
			[
				{
					"name" : "HELPSTRING",
					"value" : "Enable event monitoring"
				}
			],
			"type" : "BOOL",
			"value" : "ON"
		},
		{
			"name" : "UA_ENABLE_TYPEDESCRIPTION",
			"properties" : 
			[
				{
					"name" : "ADVANCED",
					"value" : "1"
				},
				{
					"name" : "HELPSTRING",
					"value" : "Add the type and member names to the UA_DataType structure"
				}
			],
			"type" : "BOOL",
			"value" : "ON"
		},
		{
			"name" : "UA_ENABLE_UNIT_TESTS_MEMCHECK",
			"properties" : 
			[
				{
					"name" : "ADVANCED",
					"value" : "1"
				},
				{
					"name" : "HELPSTRING",
					"value" : "Use Valgrind (Linux) or DrMemory (Windows) to detect memory leaks when running the unit tests"
				}
			],
			"type" : "BOOL",
			"value" : "ON"
		},
		{
			"name" : "UA_ENABLE_UNIT_TEST_FAILURE_HOOKS",
			"properties" : 
			[
				{
					"name" : "ADVANCED",
					"value" : "1"
				},
				{
					"name" : "HELPSTRING",
					"value" : "Add hooks to force failure modes for additional unit tests. Not for production use!"
				}
			],
			"type" : "BOOL",
			"value" : "OFF"
		},
		{
			"name" : "UA_ENABLE_VALGRIND_INTERACTIVE",
			"properties" : 
			[
				{
					"name" : "ADVANCED",
					"value" : "1"
				},
				{
					"name" : "HELPSTRING",
					"value" : "Enable dumping valgrind every iteration. CAUTION! SLOWDOWN!"
				}
			],
			"type" : "BOOL",
			"value" : "OFF"
		},
		{
			"name" : "UA_ENABLE_WEBSOCKET_SERVER",
			"properties" : 
			[
				{
					"name" : "ADVANCED",
					"value" : "1"
				},
				{
					"name" : "HELPSTRING",
					"value" : "Enable websocket support (uses libwebsockets)"
				}
			],
			"type" : "BOOL",
			"value" : "OFF"
		},
		{
			"name" : "UA_FILE_NS0",
			"properties" : 
			[
				{
					"name" : "ADVANCED",
					"value" : "1"
				},
				{
					"name" : "HELPSTRING",
					"value" : "Override the NodeSet xml file used to generate namespace zero"
				}
			],
			"type" : "BOOL",
			"value" : "OFF"
		},
		{
			"name" : "UA_FILE_NS0_BLACKLIST",
			"properties" : 
			[
				{
					"name" : "ADVANCED",
					"value" : "1"
				},
				{
					"name" : "HELPSTRING",
					"value" : "File containing blacklisted nodes which should not be included in the generated nodeset code."
				}
			],
			"type" : "BOOL",
			"value" : "OFF"
		},
		{
			"name" : "UA_FORCE_32BIT",
			"properties" : 
			[
				{
					"name" : "ADVANCED",
					"value" : "1"
				},
				{
					"name" : "HELPSTRING",
					"value" : "Force compilation as 32-bit executable"
				}
			],
			"type" : "BOOL",
			"value" : "OFF"
		},
		{
			"name" : "UA_FORCE_CPP",
			"properties" : 
			[
				{
					"name" : "ADVANCED",
					"value" : "1"
				},
				{
					"name" : "HELPSTRING",
					"value" : "Force compilation with a C++ compiler"
				}
			],
			"type" : "BOOL",
			"value" : "OFF"
		},
		{
			"name" : "UA_FORCE_WERROR",
			"properties" : 
			[
				{
					"name" : "HELPSTRING",
					"value" : "Force compilation with -Werror (or /WX on MSVC)"
				}
			],
			"type" : "BOOL",
			"value" : "OFF;OFF"
		},
		{
			"name" : "UA_LOGLEVEL",
			"properties" : 
			[
				{
					"name" : "HELPSTRING",
					"value" : "Level at which logs shall be reported"
				}
			],
			"type" : "STRING",
			"value" : "300"
		},
		{
			"name" : "UA_MSVC_FORCE_STATIC_CRT",
			"properties" : 
			[
				{
					"name" : "ADVANCED",
					"value" : "1"
				},
				{
					"name" : "HELPSTRING",
					"value" : "Force linking with the static C-runtime library when compiling to static library with MSVC"
				}
			],
			"type" : "BOOL",
			"value" : "ON"
		},
		{
			"name" : "UA_MULTITHREADING",
			"properties" : 
			[
				{
					"name" : "HELPSTRING",
					"value" : "Level of multithreading (0-99: No Multithreading, >=100: Thread-Safe API"
				}
			],
			"type" : "STRING",
			"value" : "0"
		},
		{
			"name" : "UA_NAMESPACE_ZERO",
			"properties" : 
			[
				{
					"name" : "HELPSTRING",
					"value" : "Completeness of the generated namespace zero (minimal/reduced/full/latest_1_05)"
				},
				{
					"name" : "STRINGS",
					"value" : "MINIMAL;REDUCED;FULL;LATEST_1_05"
				}
			],
			"type" : "STRING",
			"value" : "REDUCED"
		},
		{
			"name" : "UA_NODESET_NS0_HEADERS",
			"properties" : 
			[
				{
					"name" : "HELPSTRING",
					"value" : "UA_NODESET_NS0 header files"
				}
			],
			"type" : "INTERNAL",
			"value" : "/Users/brk/_private/repos/utils/Camel-Snake-Util/cmake-build-debug-system/vendor/open62541pp/3rdparty/open62541/src_generated/open62541/namespace0_generated.h"
		},
		{
			"name" : "UA_NODESET_NS0_SOURCES",
			"properties" : 
			[
				{
					"name" : "HELPSTRING",
					"value" : "UA_NODESET_NS0 source files"
				}
			],
			"type" : "INTERNAL",
			"value" : "/Users/brk/_private/repos/utils/Camel-Snake-Util/cmake-build-debug-system/vendor/open62541pp/3rdparty/open62541/src_generated/open62541/namespace0_generated.c"
		},
		{
			"name" : "UA_NODESET_NS0_TARGET",
			"properties" : 
			[
				{
					"name" : "HELPSTRING",
					"value" : "UA_NODESET_NS0 target"
				}
			],
			"type" : "INTERNAL",
			"value" : "open62541-generator-namespace"
		},
		{
			"name" : "UA_PACK_DEBIAN",
			"properties" : 
			[
				{
					"name" : "ADVANCED",
					"value" : "1"
				},
				{
					"name" : "HELPSTRING",
					"value" : "Special build switch used in .deb packaging"
				}
			],
			"type" : "BOOL",
			"value" : "OFF"
		},
		{
			"name" : "UA_TRANSPORT_HEADERS",
			"properties" : 
			[
				{
					"name" : "HELPSTRING",
					"value" : "transport header files"
				}
			],
			"type" : "INTERNAL",
			"value" : "/Users/brk/_private/repos/utils/Camel-Snake-Util/cmake-build-debug-system/vendor/open62541pp/3rdparty/open62541/src_generated/open62541/transport_generated.h;/Users/brk/_private/repos/utils/Camel-Snake-Util/cmake-build-debug-system/vendor/open62541pp/3rdparty/open62541/src_generated/open62541/transport_generated_handling.h"
		},
		{
			"name" : "UA_TRANSPORT_SOURCES",
			"properties" : 
			[
				{
					"name" : "HELPSTRING",
					"value" : "transport source files"
				}
			],
			"type" : "INTERNAL",
			"value" : "/Users/brk/_private/repos/utils/Camel-Snake-Util/cmake-build-debug-system/vendor/open62541pp/3rdparty/open62541/src_generated/open62541/transport_generated.c"
		},
		{
			"name" : "UA_TYPES_HEADERS",
			"properties" : 
			[
				{
					"name" : "HELPSTRING",
					"value" : "types header files"
				}
			],
			"type" : "INTERNAL",
			"value" : "/Users/brk/_private/repos/utils/Camel-Snake-Util/cmake-build-debug-system/vendor/open62541pp/3rdparty/open62541/src_generated/open62541/types_generated.h;/Users/brk/_private/repos/utils/Camel-Snake-Util/cmake-build-debug-system/vendor/open62541pp/3rdparty/open62541/src_generated/open62541/types_generated_handling.h"
		},
		{
			"name" : "UA_TYPES_SOURCES",
			"properties" : 
			[
				{
					"name" : "HELPSTRING",
					"value" : "types source files"
				}
			],
			"type" : "INTERNAL",
			"value" : "/Users/brk/_private/repos/utils/Camel-Snake-Util/cmake-build-debug-system/vendor/open62541pp/3rdparty/open62541/src_generated/open62541/types_generated.c"
		},
		{
			"name" : "UA_VALGRIND_INTERACTIVE_INTERVAL",
			"properties" : 
			[
				{
					"name" : "ADVANCED",
					"value" : "1"
				},
				{
					"name" : "HELPSTRING",
					"value" : "The number of iterations to wait before creating the next dump"
				}
			],
			"type" : "STRING",
			"value" : "1000"
		},
		{
			"name" : "Vulkan_GLSLANG_VALIDATOR_EXECUTABLE",
			"properties" : 
			[
				{
					"name" : "ADVANCED",
					"value" : "1"
				},
				{
					"name" : "HELPSTRING",
					"value" : "Path to a program."
				}
			],
			"type" : "FILEPATH",
			"value" : "/usr/local/bin/glslangValidator"
		},
		{
			"name" : "Vulkan_GLSLC_EXECUTABLE",
			"properties" : 
			[
				{
					"name" : "ADVANCED",
					"value" : "1"
				},
				{
					"name" : "HELPSTRING",
					"value" : "Path to a program."
				}
			],
			"type" : "FILEPATH",
			"value" : "/usr/local/bin/glslc"
		},
		{
			"name" : "Vulkan_INCLUDE_DIR",
			"properties" : 
			[
				{
					"name" : "ADVANCED",
					"value" : "1"
				},
				{
					"name" : "HELPSTRING",
					"value" : "Path to a file."
				}
			],
			"type" : "PATH",
			"value" : "/usr/local/include"
		},
		{
			"name" : "Vulkan_LIBRARY",
			"properties" : 
			[
				{
					"name" : "ADVANCED",
					"value" : "1"
				},
				{
					"name" : "HELPSTRING",
					"value" : "Path to a library."
				}
			],
			"type" : "FILEPATH",
			"value" : "/usr/local/lib/libvulkan.dylib"
		},
		{
			"name" : "XELATEX_COMPILER",
			"properties" : 
			[
				{
					"name" : "ADVANCED",
					"value" : "1"
				},
				{
					"name" : "HELPSTRING",
					"value" : "Path to a program."
				}
			],
			"type" : "FILEPATH",
			"value" : "XELATEX_COMPILER-NOTFOUND"
		},
		{
			"name" : "XINDY_COMPILER",
			"properties" : 
			[
				{
					"name" : "ADVANCED",
					"value" : "1"
				},
				{
					"name" : "HELPSTRING",
					"value" : "Path to a program."
				}
			],
			"type" : "FILEPATH",
			"value" : "XINDY_COMPILER-NOTFOUND"
		},
		{
			"name" : "_GNUInstallDirs_LAST_CMAKE_INSTALL_PREFIX",
			"properties" : 
			[
				{
					"name" : "HELPSTRING",
					"value" : "CMAKE_INSTALL_PREFIX during last run"
				}
			],
			"type" : "INTERNAL",
			"value" : "/usr/local"
		},
		{
			"name" : "imgui_BINARY_DIR",
			"properties" : 
			[
				{
					"name" : "HELPSTRING",
					"value" : "Value Computed by CMake"
				}
			],
			"type" : "STATIC",
			"value" : "/Users/brk/_private/repos/utils/Camel-Snake-Util/cmake-build-debug-system/vendor/imgui"
		},
		{
			"name" : "imgui_IS_TOP_LEVEL",
			"properties" : 
			[
				{
					"name" : "HELPSTRING",
					"value" : "Value Computed by CMake"
				}
			],
			"type" : "STATIC",
			"value" : "OFF"
		},
		{
			"name" : "imgui_SOURCE_DIR",
			"properties" : 
			[
				{
					"name" : "HELPSTRING",
					"value" : "Value Computed by CMake"
				}
			],
			"type" : "STATIC",
			"value" : "/Users/brk/_private/repos/utils/Camel-Snake-Util/vendor/imgui"
		},
		{
			"name" : "magic_enum_BINARY_DIR",
			"properties" : 
			[
				{
					"name" : "HELPSTRING",
					"value" : "Value Computed by CMake"
				}
			],
			"type" : "STATIC",
			"value" : "/Users/brk/_private/repos/utils/Camel-Snake-Util/cmake-build-debug-system/vendor/imgui/HBUI/vendor/magic_enum"
		},
		{
			"name" : "magic_enum_IS_TOP_LEVEL",
			"properties" : 
			[
				{
					"name" : "HELPSTRING",
					"value" : "Value Computed by CMake"
				}
			],
			"type" : "STATIC",
			"value" : "OFF"
		},
		{
			"name" : "magic_enum_SOURCE_DIR",
			"properties" : 
			[
				{
					"name" : "HELPSTRING",
					"value" : "Value Computed by CMake"
				}
			],
			"type" : "STATIC",
			"value" : "/Users/brk/_private/repos/utils/Camel-Snake-Util/vendor/imgui/HBUI/vendor/magic_enum"
		},
		{
			"name" : "open62541++_BINARY_DIR",
			"properties" : 
			[
				{
					"name" : "HELPSTRING",
					"value" : "Value Computed by CMake"
				}
			],
			"type" : "STATIC",
			"value" : "/Users/brk/_private/repos/utils/Camel-Snake-Util/cmake-build-debug-system/vendor/open62541pp"
		},
		{
			"name" : "open62541++_IS_TOP_LEVEL",
			"properties" : 
			[
				{
					"name" : "HELPSTRING",
					"value" : "Value Computed by CMake"
				}
			],
			"type" : "STATIC",
			"value" : "OFF"
		},
		{
			"name" : "open62541++_SOURCE_DIR",
			"properties" : 
			[
				{
					"name" : "HELPSTRING",
					"value" : "Value Computed by CMake"
				}
			],
			"type" : "STATIC",
			"value" : "/Users/brk/_private/repos/utils/Camel-Snake-Util/vendor/open62541pp"
		},
		{
			"name" : "open62541_BINARY_DIR",
			"properties" : 
			[
				{
					"name" : "HELPSTRING",
					"value" : "Value Computed by CMake"
				}
			],
			"type" : "STATIC",
			"value" : "/Users/brk/_private/repos/utils/Camel-Snake-Util/cmake-build-debug-system/vendor/open62541pp/3rdparty/open62541"
		},
		{
			"name" : "open62541_IS_TOP_LEVEL",
			"properties" : 
			[
				{
					"name" : "HELPSTRING",
					"value" : "Value Computed by CMake"
				}
			],
			"type" : "STATIC",
			"value" : "OFF"
		},
		{
			"name" : "open62541_SOURCE_DIR",
			"properties" : 
			[
				{
					"name" : "HELPSTRING",
					"value" : "Value Computed by CMake"
				}
			],
			"type" : "STATIC",
			"value" : "/Users/brk/_private/repos/utils/Camel-Snake-Util/vendor/open62541pp/3rdparty/open62541"
		},
		{
			"name" : "spdlog_BINARY_DIR",
			"properties" : 
			[
				{
					"name" : "HELPSTRING",
					"value" : "Value Computed by CMake"
				}
			],
			"type" : "STATIC",
			"value" : "/Users/brk/_private/repos/utils/Camel-Snake-Util/cmake-build-debug-system/vendor/imgui/HBUI/vendor/spdlog"
		},
		{
			"name" : "spdlog_IS_TOP_LEVEL",
			"properties" : 
			[
				{
					"name" : "HELPSTRING",
					"value" : "Value Computed by CMake"
				}
			],
			"type" : "STATIC",
			"value" : "OFF"
		},
		{
			"name" : "spdlog_LIB_DEPENDS",
			"properties" : 
			[
				{
					"name" : "HELPSTRING",
					"value" : "Dependencies for the target"
				}
			],
			"type" : "STATIC",
			"value" : "general;fmt::fmt;"
		},
		{
			"name" : "spdlog_SOURCE_DIR",
			"properties" : 
			[
				{
					"name" : "HELPSTRING",
					"value" : "Value Computed by CMake"
				}
			],
			"type" : "STATIC",
			"value" : "/Users/brk/_private/repos/utils/Camel-Snake-Util/vendor/imgui/HBUI/vendor/spdlog"
		}
	],
	"kind" : "cache",
	"version" : 
	{
		"major" : 2,
		"minor" : 0
	}
}
